Workbook

Sheet 汇总
A3: KPI | C3: 权重 | D3: 北京 | E3: 贵阳 | F3: 昆明 | G3: 滨湖 | H3: 长沙 | I3: 闽江 | J3: 北城 | K3: 罗源 | L3: 连江 | M3: 宁波 | N3: 腾冲 | O3: 版纳 | P3: 阜阳
A4: 经营收益（35%） | B4: 当期收费率（15%） | C4: 0.15 | D4: =ROUND(INDEX(收费率!$F$4:$F$16,MATCH(汇总!D3,收费率!$E$4:$E$16,0)),1) -> 67.2 | E4: =ROUND(INDEX(收费率!$F$4:$F$16,MATCH(汇总!E3,收费率!$E$4:$E$16,0)),1) -> 64.5 | F4: =ROUND(INDEX(收费率!$F$4:$F$16,MATCH(汇总!F3,收费率!$E$4:$E$16,0)),1) -> 74.9 | G4: =ROUND(INDEX(收费率!$F$4:$F$16,MATCH(汇总!G3,收费率!$E$4:$E$16,0)),1) -> 63.9 | H4: =ROUND(INDEX(收费率!$F$4:$F$16,MATCH(汇总!H3,收费率!$E$4:$E$16,0)),1) -> 60 | I4: =ROUND(INDEX(收费率!$F$4:$F$16,MATCH(汇总!I3,收费率!$E$4:$E$16,0)),1) -> 57.4 | J4: =ROUND(INDEX(收费率!$F$4:$F$16,MATCH(汇总!J3,收费率!$E$4:$E$16,0)),1) -> 74.8 | K4: =ROUND(INDEX(收费率!$F$4:$F$16,MATCH(汇总!K3,收费率!$E$4:$E$16,0)),1) -> 78.1 | ... P4: =ROUND(INDEX(收费率!$F$4:$F$16,MATCH(汇总!P3,收费率!$E$4:$E$16,0)),1) -> 75.8
B5: 历欠收费率（10%） | C5: 0.1 | D5: =ROUND(INDEX(收费率!$F$23:$F$35,MATCH(汇总!D3,收费率!$E$23:$E$35,0)),1) -> 53.8 | E5: =ROUND(INDEX(收费率!$F$23:$F$35,MATCH(汇总!E3,收费率!$E$23:$E$35,0)),1) -> 50.5 | F5: =ROUND(INDEX(收费率!$F$23:$F$35,MATCH(汇总!F3,收费率!$E$23:$E$35,0)),1) -> 62.9 | G5: =ROUND(INDEX(收费率!$F$23:$F$35,MATCH(汇总!G3,收费率!$E$23:$E$35,0)),1) -> 34.9 | H5: =ROUND(INDEX(收费率!$F$23:$F$35,MATCH(汇总!H3,收费率!$E$23:$E$35,0)),1) -> 63.9 | I5: =ROUND(INDEX(收费率!$F$23:$F$35,MATCH(汇总!I3,收费率!$E$23:$E$35,0)),1) -> 52.2 | J5: =ROUND(INDEX(收费率!$F$23:$F$35,MATCH(汇总!J3,收费率!$E$23:$E$35,0)),1) -> 47.9 | K5: =ROUND(INDEX(收费率!$F$23:$F$35,MATCH(汇总!K3,收费率!$E$23:$E$35,0)),1) -> 63.3 | ... P5: =ROUND(INDEX(收费率!$F$23:$F$35,MATCH(汇总!P3,收费率!$E$23:$E$35,0)),1) -> 68.4
B6: 空间资源指标完成（10%） | C6: 0.1 | D6: {=MAX(0,ROUND(INDEX(空间资源!$G$3:$G$15,MATCH(D3,空间资源!$F$3:$F$15,0)),1))} -> 0 | E6: {=MAX(0,ROUND(INDEX(空间资源!$G$3:$G$15,MATCH(E3,空间资源!$F$3:$F$15,0)),1))} -> 0 | F6: {=MAX(0,ROUND(INDEX(空间资源!$G$3:$G$15,MATCH(F3,空间资源!$F$3:$F$15,0)),1))} -> 0 | G6: {=MAX(0,ROUND(INDEX(空间资源!$G$3:$G$15,MATCH(G3,空间资源!$F$3:$F$15,0)),1))} -> 0 | H6: {=MAX(0,ROUND(INDEX(空间资源!$G$3:$G$15,MATCH(H3,空间资源!$F$3:$F$15,0)),1))} -> 0 | I6: {=MAX(0,ROUND(INDEX(空间资源!$G$3:$G$15,MATCH(I3,空间资源!$F$3:$F$15,0)),1))} -> 0 | J6: {=MAX(0,ROUND(INDEX(空间资源!$G$3:$G$15,MATCH(J3,空间资源!$F$3:$F$15,0)),1))} -> 0 | K6: {=MAX(0,ROUND(INDEX(空间资源!$G$3:$G$15,MATCH(K3,空间资源!$F$3:$F$15,0)),1))} -> 0 | ... P6: {=MAX(0,ROUND(INDEX(空间资源!$G$3:$G$15,MATCH(P3,空间资源!$F$3:$F$15,0)),1))} -> 0
A7: 客户服务（35%） | B7: 业主满意度（25%） | C7: 0.25 | D7: =ROUND(INDEX(业主满意度!$J$4:$J$16,MATCH(D3,业主满意度!$H$4:$H$16,0)),1) -> 70 | E7: =ROUND(INDEX(业主满意度!$J$4:$J$16,MATCH(E3,业主满意度!$H$4:$H$16,0)),1) -> 70 | F7: =ROUND(INDEX(业主满意度!$J$4:$J$16,MATCH(F3,业主满意度!$H$4:$H$16,0)),1) -> 70 | G7: =ROUND(INDEX(业主满意度!$J$4:$J$16,MATCH(G3,业主满意度!$H$4:$H$16,0)),1) -> 70 | H7: =ROUND(INDEX(业主满意度!$J$4:$J$16,MATCH(H3,业主满意度!$H$4:$H$16,0)),1) -> 70 | I7: =ROUND(INDEX(业主满意度!$J$4:$J$16,MATCH(I3,业主满意度!$H$4:$H$16,0)),1) -> 70 | J7: =ROUND(INDEX(业主满意度!$J$4:$J$16,MATCH(J3,业主满意度!$H$4:$H$16,0)),1) -> 70 | K7: =ROUND(INDEX(业主满意度!$J$4:$J$16,MATCH(K3,业主满意度!$H$4:$H$16,0)),1) -> 70 | ... P7: =ROUND(INDEX(业主满意度!$J$4:$J$16,MATCH(P3,业主满意度!$H$4:$H$16,0)),1) -> 70
B8: 投诉完成率（10%） | C8: 0.1 | D8: =ROUND(INDEX(投诉完成率!$P$5:$P$17,MATCH(D3,投诉完成率!$O$5:$O$17,0)),1) -> 80 | E8: =ROUND(INDEX(投诉完成率!$P$5:$P$17,MATCH(E3,投诉完成率!$O$5:$O$17,0)),1) -> 100 | F8: =ROUND(INDEX(投诉完成率!$P$5:$P$17,MATCH(F3,投诉完成率!$O$5:$O$17,0)),1) -> 95 | G8: =ROUND(INDEX(投诉完成率!$P$5:$P$17,MATCH(G3,投诉完成率!$O$5:$O$17,0)),1) -> 85 | H8: =ROUND(INDEX(投诉完成率!$P$5:$P$17,MATCH(H3,投诉完成率!$O$5:$O$17,0)),1) -> 90 | I8: =ROUND(INDEX(投诉完成率!$P$5:$P$17,MATCH(I3,投诉完成率!$O$5:$O$17,0)),1) -> 100 | J8: =ROUND(INDEX(投诉完成率!$P$5:$P$17,MATCH(J3,投诉完成率!$O$5:$O$17,0)),1) -> 90 | K8: =ROUND(INDEX(投诉完成率!$P$5:$P$17,MATCH(K3,投诉完成率!$O$5:$O$17,0)),1) -> 67.5 | ... P8: =ROUND(INDEX(投诉完成率!$P$5:$P$17,MATCH(P3,投诉完成率!$O$5:$O$17,0)),1) -> 80.8
A9: 工程管控（20%） | B9: 设备设施管理（10%） | C9: 0.1 | D9: =ROUND(INDEX(设备设施管理!$H$3:$H$15,MATCH(D3,设备设施管理!$G$3:$G$15,0)),1) -> 0 | E9: =ROUND(INDEX(设备设施管理!$H$3:$H$15,MATCH(E3,设备设施管理!$G$3:$G$15,0)),1) -> 0 | F9: =ROUND(INDEX(设备设施管理!$H$3:$H$15,MATCH(F3,设备设施管理!$G$3:$G$15,0)),1) -> 0 | G9: =ROUND(INDEX(设备设施管理!$H$3:$H$15,MATCH(G3,设备设施管理!$G$3:$G$15,0)),1) -> 0 | H9: =ROUND(INDEX(设备设施管理!$H$3:$H$15,MATCH(H3,设备设施管理!$G$3:$G$15,0)),1) -> 0 | I9: =ROUND(INDEX(设备设施管理!$H$3:$H$15,MATCH(I3,设备设施管理!$G$3:$G$15,0)),1) -> 0 | J9: =ROUND(INDEX(设备设施管理!$H$3:$H$15,MATCH(J3,设备设施管理!$G$3:$G$15,0)),1) -> 0 | K9: =ROUND(INDEX(设备设施管理!$H$3:$H$15,MATCH(K3,设备设施管理!$G$3:$G$15,0)),1) -> 0 | ... P9: =ROUND(INDEX(设备设施管理!$H$3:$H$15,MATCH(P3,设备设施管理!$G$3:$G$15,0)),1) -> 0
B10: 自用能耗成本管控（10%） | C10: 0.1 | D10: =ROUND(INDEX(自用能耗成本!$K$3:$K$15,MATCH(D3,自用能耗成本!$J$3:$J$15,0)),1) -> 119 | E10: =ROUND(INDEX(自用能耗成本!$K$3:$K$15,MATCH(E3,自用能耗成本!$J$3:$J$15,0)),1) -> 111.4 | F10: =ROUND(INDEX(自用能耗成本!$K$3:$K$15,MATCH(F3,自用能耗成本!$J$3:$J$15,0)),1) -> 79.4 | G10: =ROUND(INDEX(自用能耗成本!$K$3:$K$15,MATCH(G3,自用能耗成本!$J$3:$J$15,0)),1) -> 120 | H10: =ROUND(INDEX(自用能耗成本!$K$3:$K$15,MATCH(H3,自用能耗成本!$J$3:$J$15,0)),1) -> 70.6 | I10: =ROUND(INDEX(自用能耗成本!$K$3:$K$15,MATCH(I3,自用能耗成本!$J$3:$J$15,0)),1) -> 120 | J10: =ROUND(INDEX(自用能耗成本!$K$3:$K$15,MATCH(J3,自用能耗成本!$J$3:$J$15,0)),1) -> 113.5 | K10: =ROUND(INDEX(自用能耗成本!$K$3:$K$15,MATCH(K3,自用能耗成本!$J$3:$J$15,0)),1) -> 99.6 | ... P10: =ROUND(INDEX(自用能耗成本!$K$3:$K$15,MATCH(P3,自用能耗成本!$J$3:$J$15,0)),1) -> 120
A11: 效率管理（10%） | B11: 基础信息维护合格率（5%） | C11: 0.05 | D11: =ROUND(INDEX(基础信息抽查!$Q$3:$Q$15,MATCH(D3,基础信息抽查!$O$3:$O$15,0)),1) -> 95.3 | E11: =ROUND(INDEX(基础信息抽查!$Q$3:$Q$15,MATCH(E3,基础信息抽查!$O$3:$O$15,0)),1) -> 100 | F11: =ROUND(INDEX(基础信息抽查!$Q$3:$Q$15,MATCH(F3,基础信息抽查!$O$3:$O$15,0)),1) -> 100 | G11: =ROUND(INDEX(基础信息抽查!$Q$3:$Q$15,MATCH(G3,基础信息抽查!$O$3:$O$15,0)),1) -> 69.5 | H11: =ROUND(INDEX(基础信息抽查!$Q$3:$Q$15,MATCH(H3,基础信息抽查!$O$3:$O$15,0)),1) -> 89.5 | I11: =ROUND(INDEX(基础信息抽查!$Q$3:$Q$15,MATCH(I3,基础信息抽查!$O$3:$O$15,0)),1) -> 93.8 | J11: =ROUND(INDEX(基础信息抽查!$Q$3:$Q$15,MATCH(J3,基础信息抽查!$O$3:$O$15,0)),1) -> 95.3 | K11: =ROUND(INDEX(基础信息抽查!$Q$3:$Q$15,MATCH(K3,基础信息抽查!$O$3:$O$15,0)),1) -> 100 | ... P11: =ROUND(INDEX(基础信息抽查!$Q$3:$Q$15,MATCH(P3,基础信息抽查!$O$3:$O$15,0)),1) -> 96
B12: 400电话知晓率（5%） | C12: 0.05 | D12: =ROUND(INDEX('400知晓率'!$R$3:$R$15,MATCH(D3,'400知晓率'!$P$3:$P$15,0)),1) -> 141.7 | E12: =ROUND(INDEX('400知晓率'!$R$3:$R$15,MATCH(E3,'400知晓率'!$P$3:$P$15,0)),1) -> 104.6 | F12: =ROUND(INDEX('400知晓率'!$R$3:$R$15,MATCH(F3,'400知晓率'!$P$3:$P$15,0)),1) -> 113.7 | G12: =ROUND(INDEX('400知晓率'!$R$3:$R$15,MATCH(G3,'400知晓率'!$P$3:$P$15,0)),1) -> 92.8 | H12: =ROUND(INDEX('400知晓率'!$R$3:$R$15,MATCH(H3,'400知晓率'!$P$3:$P$15,0)),1) -> 100.2 | I12: =ROUND(INDEX('400知晓率'!$R$3:$R$15,MATCH(I3,'400知晓率'!$P$3:$P$15,0)),1) -> 108.6 | J12: =ROUND(INDEX('400知晓率'!$R$3:$R$15,MATCH(J3,'400知晓率'!$P$3:$P$15,0)),1) -> 101.1 | K12: =ROUND(INDEX('400知晓率'!$R$3:$R$15,MATCH(K3,'400知晓率'!$P$3:$P$15,0)),1) -> 111.5 | ... P12: =ROUND(INDEX('400知晓率'!$R$3:$R$15,MATCH(P3,'400知晓率'!$P$3:$P$15,0)),1) -> 112.3
A13: 重大事项扣罚 | C13: —— | D13: 0 | E13: 0 | F13: 0 | G13: 0 | H13: 0 | I13: 0 | J13: 0 | K13: 0 | L13: 0 | M13: 0 | N13: 0 | O13: 0 | P13: 0
A14: 总分 | C14: —— | D14: =D4*$C$4+D5*$C$5+D6*$C$6+D7*$C$7+D8*$C$8+D9*$C$9+D10*$C$10+D11*$C$11+D12*$C$12 -> 64.71 | E14: =E4*$C$4+E5*$C$5+E6*$C$6+E7*$C$7+E8*$C$8+E9*$C$9+E10*$C$10+E11*$C$11+E12*$C$12 -> 63.595 | F14: =F4*$C$4+F5*$C$5+F6*$C$6+F7*$C$7+F8*$C$8+F9*$C$9+F10*$C$10+F11*$C$11+F12*$C$12 -> 63.15 | G14: =G4*$C$4+G5*$C$5+G6*$C$6+G7*$C$7+G8*$C$8+G9*$C$9+G10*$C$10+G11*$C$11+G12*$C$12 -> 59.19 | H14: =H4*$C$4+H5*$C$5+H6*$C$6+H7*$C$7+H8*$C$8+H9*$C$9+H10*$C$10+H11*$C$11+H12*$C$12 -> 58.435 | I14: =I4*$C$4+I5*$C$5+I6*$C$6+I7*$C$7+I8*$C$8+I9*$C$9+I10*$C$10+I11*$C$11+I12*$C$12 -> 63.45 | J14: =J4*$C$4+J5*$C$5+J6*$C$6+J7*$C$7+J8*$C$8+J9*$C$9+J10*$C$10+J11*$C$11+J12*$C$12 -> 63.68 | K14: =K4*$C$4+K5*$C$5+K6*$C$6+K7*$C$7+K8*$C$8+K9*$C$9+K10*$C$10+K11*$C$11+K12*$C$12 -> 62.83 | ... P14: =P4*$C$4+P5*$C$5+P6*$C$6+P7*$C$7+P8*$C$8+P9*$C$9+P10*$C$10+P11*$C$11+P12*$C$12 -> 66.205
A15: 排名 | C15: —— | D15: =RANK(D14,$D$14:$P$14) -> 3 | E15: =RANK(E14,$D$14:$P$14) -> 5 | F15: =RANK(F14,$D$14:$P$14) -> 7 | G15: =RANK(G14,$D$14:$P$14) -> 11 | H15: =RANK(H14,$D$14:$P$14) -> 12 | I15: =RANK(I14,$D$14:$P$14) -> 6 | J15: =RANK(J14,$D$14:$P$14) -> 4 | K15: =RANK(K14,$D$14:$P$14) -> 8 | ... P15: =RANK(P14,$D$14:$P$14) -> 1
A19: 仅保留1位小数
A20: KPI | D20: 北京 | E20: 贵阳 | F20: 昆明 | G20: 滨湖 | H20: 长沙 | I20: 闽江 | J20: 北城 | K20: 罗源 | L20: 连江 | M20: 宁波 | N20: 腾冲 | O20: 版纳 | P20: 阜阳
A21: 经营收益（35%） | B21: 当期收费率（15%） | C21: 0.15 | D21: =ROUND(D4*0.15,1) -> 10.1 | E21: =ROUND(E4*0.15,1) -> 9.7 | F21: =ROUND(F4*0.15,1) -> 11.2 | G21: =ROUND(G4*0.15,1) -> 9.6 | H21: =ROUND(H4*0.15,1) -> 9 | I21: =ROUND(I4*0.15,1) -> 8.6 | J21: =ROUND(J4*0.15,1) -> 11.2 | K21: =ROUND(K4*0.15,1) -> 11.7 | ... P21: =ROUND(P4*0.15,1) -> 11.4
B22: 历欠收费率（10%） | C22: 0.1 | D22: =ROUND(D5*0.1,1) -> 5.4 | E22: =ROUND(E5*0.1,1) -> 5.1 | F22: =ROUND(F5*0.1,1) -> 6.3 | G22: =ROUND(G5*0.1,1) -> 3.5 | H22: =ROUND(H5*0.1,1) -> 6.4 | I22: =ROUND(I5*0.1,1) -> 5.2 | J22: =ROUND(J5*0.1,1) -> 4.8 | K22: =ROUND(K5*0.1,1) -> 6.3 | ... P22: =ROUND(P5*0.1,1) -> 6.8
B23: 空间资源指标完成（10%） | C23: 0.1 | D23: =ROUND(D6*0.1,1) -> 0 | E23: =ROUND(E6*0.1,1) -> 0 | F23: =ROUND(F6*0.1,1) -> 0 | G23: =ROUND(G6*0.1,1) -> 0 | H23: =ROUND(H6*0.1,1) -> 0 | I23: =ROUND(I6*0.1,1) -> 0 | J23: =ROUND(J6*0.1,1) -> 0 | K23: =ROUND(K6*0.1,1) -> 0 | ... P23: =ROUND(P6*0.1,1) -> 0
A24: 客户服务（35%） | B24: 业主满意度（25%） | C24: 0.25 | D24: =ROUND(D7*0.25,1) -> 17.5 | E24: =ROUND(E7*0.25,1) -> 17.5 | F24: =ROUND(F7*0.25,1) -> 17.5 | G24: =ROUND(G7*0.25,1) -> 17.5 | H24: =ROUND(H7*0.25,1) -> 17.5 | I24: =ROUND(I7*0.25,1) -> 17.5 | J24: =ROUND(J7*0.25,1) -> 17.5 | K24: =ROUND(K7*0.25,1) -> 17.5 | ... P24: =ROUND(P7*0.25,1) -> 17.5
B25: 投诉完成率（10%） | C25: 0.1 | D25: =ROUND(D8*0.1,1) -> 8 | E25: =ROUND(E8*0.1,1) -> 10 | F25: =ROUND(F8*0.1,1) -> 9.5 | G25: =ROUND(G8*0.1,1) -> 8.5 | H25: =ROUND(H8*0.1,1) -> 9 | I25: =ROUND(I8*0.1,1) -> 10 | J25: =ROUND(J8*0.1,1) -> 9 | K25: =ROUND(K8*0.1,1) -> 6.8 | ... P25: =ROUND(P8*0.1,1) -> 8.1
A26: 工程管控（15%） | B26: 设备设施管理（10%） | C26: 0.1 | D26: =ROUND(D9*0.1,1) -> 0 | E26: =ROUND(E9*0.1,1) -> 0 | F26: =ROUND(F9*0.1,1) -> 0 | G26: =ROUND(G9*0.1,1) -> 0 | H26: =ROUND(H9*0.1,1) -> 0 | I26: =ROUND(I9*0.1,1) -> 0 | J26: =ROUND(J9*0.1,1) -> 0 | K26: =ROUND(K9*0.1,1) -> 0 | ... P26: =ROUND(P9*0.1,1) -> 0
B27: 自用能耗成本管控（10%） | C27: 0.1 | D27: =ROUND(D10*0.05,1) -> 6 | E27: =ROUND(E10*0.05,1) -> 5.6 | F27: =ROUND(F10*0.05,1) -> 4 | G27: =ROUND(G10*0.05,1) -> 6 | H27: =ROUND(H10*0.05,1) -> 3.5 | I27: =ROUND(I10*0.05,1) -> 6 | J27: =ROUND(J10*0.05,1) -> 5.7 | K27: =ROUND(K10*0.05,1) -> 5 | ... P27: =ROUND(P10*0.05,1) -> 6
A28: 效率管理（10%） | B28: 客户信息维护（10%） | C28: 0.1 | D28: =ROUND(D11*0.05,1)+ROUND(D12*0.05,1) -> 11.9 | E28: =ROUND(E11*0.05,1)+ROUND(E12*0.05,1) -> 10.2 | F28: =ROUND(F11*0.05,1)+ROUND(F12*0.05,1) -> 10.7 | G28: =ROUND(G11*0.05,1)+ROUND(G12*0.05,1) -> 8.1 | H28: =ROUND(H11*0.05,1)+ROUND(H12*0.05,1) -> 9.5 | I28: =ROUND(I11*0.05,1)+ROUND(I12*0.05,1) -> 10.1 | J28: =ROUND(J11*0.05,1)+ROUND(J12*0.05,1) -> 9.9 | K28: =ROUND(K11*0.05,1)+ROUND(K12*0.05,1) -> 10.6 | ... P28: =ROUND(P11*0.05,1)+ROUND(P12*0.05,1) -> 10.4
A29: 重大事项扣罚 | D29: =D13 -> 0 | E29: =E13 -> 0 | F29: 0 | G29: =G13 -> 0 | H29: =H13 -> 0 | I29: =I13 -> 0 | J29: =J13 -> 0 | K29: =K13 -> 0 | L29: =L13 -> 0 | M29: =M13 -> 0 | N29: =N13 -> 0 | ... P29: =P13 -> 0
A30: 总分 | D30: =SUM(D21:D29) -> 58.9 | E30: =SUM(E21:E29) -> 58.1 | F30: =SUM(F21:F29) -> 59.2 | G30: =SUM(G21:G29) -> 53.2 | H30: =SUM(H21:H29) -> 54.9 | I30: =SUM(I21:I29) -> 57.4 | J30: =SUM(J21:J29) -> 58.1 | K30: =SUM(K21:K29) -> 57.9 | ... P30: =SUM(P21:P29) -> 60.2
A31: 排名 | D31: =RANK(D30,$D$30:$P$30) -> 4 | E31: =RANK(E30,$D$30:$P$30) -> 5 | F31: =RANK(F30,$D$30:$P$30) -> 2 | G31: =RANK(G30,$D$30:$P$30) -> 12 | H31: =RANK(H30,$D$30:$P$30) -> 10 | I31: =RANK(I30,$D$30:$P$30) -> 8 | J31: =RANK(J30,$D$30:$P$30) -> 5 | K31: =RANK(K30,$D$30:$P$30) -> 7 | ... P31: =RANK(P30,$D$30:$P$30) -> 1
A33: 2025年城市公司KPI考核指标得分

Sheet 26年考核标准
A1: 附件一
A2: 品质服务精细化管理KPI
A3: 序号 | B3: 类型 | C3: KPI指标 | D3: 权重 | E3: 指标说明 | F3: 评分标准 | G3: 备注
A4: 1 | B4: 经营收益(35%) | C4: 当期收费率 | D4: 0.15 | E4: 当期收费率R=实收金额/应收金额*100% | F4: 当期收费率R以综合费项全年收费率指标为基准线 ①当R=基准线时，得100分 ②当R＞基准线时，较基准线每上升1%加3分（封顶120分），得分=100+(R-基准线)/1%*3 ③当R＜基准线时，较基准线每下降1%减2分，得分=100-(基准线-R)/1%*2 | G4: 含公司自建、外拓项目综合收费项（全口径），详见附件四
A5: 2 | C5: 历欠收费率 | D5: 0.1 | E5: 历欠收费率R=实收金额/应收金额*100% | F5: 历欠收费率R以全年欠费回款指标为基准线 ①当R=基准线时，得100分 ②当R＞基准线时，较基准线每上升1%加3分（封顶120分），得分=100+(R-基准线)/1%*3 ③当R＜基准线时，较基准线每下降1%减2分，得分=100-(基准线-R)/1%*2 | G5: 含公司自建、外拓多业权项目（在管+撤场1年内），详见附件四
A6: 3 | C6: 空间资源指标完成率 | D6: 0.1 | E6: 空间资源指标完成率R=实收金额/指标金额*100% | F6: 空间资源指标完成率R以全年空间资源经营指标为基准线 ①当R=基准线时，得100分 ②当R＞基准线时，较基准线每上升1%加3分（封顶120分），得分=100+(R-基准线)/1%*3 ③当R＜基准线时，较基准线每下降1%减2分，得分=100-(基准线-R)/1%*2 | G6: 自建项目，详见附件四
A7: 4 | B7: 客户服务(35%) | C7: 业主满意度 | D7: 0.25 | E7: 400调查年度客户满意度评分 | F7: 业主满意度R以各公司上年度得分为基准线： ①目标值≥75分，基础分100分；目标值＜75分，基础分90分 ②目标值≥80分：实际值较目标值每上升1%加2分（封顶120分），每下降1%减1分 ③75分≤目标值＜80分：实际值较目标值每上升1%加1分，每下降1%减2分 ④目标值＜75分：实际值未达75分，较目标值每上升1%分差加分[（实际值-目标值）/（75-目标值）*10分]，每下降1%减3分；实际值达75分以上按②、③规则核算 | G7: 1、自建项目 2、客户满意度评分以400电话调查结果为准
A8: 5 | C8: 投诉处理 完成率 | D8: 0.1 | E8: 投诉处理完成率R | F8: 投诉处理完成率R以75%为基准线，得分=基础分*满意度系数 ①基础分：投诉处理完成率按月度核算，每月R均75%(含）以上，得100分，单月不达标，-5分/次 ②满意度系数：以年度投诉处理满意度确定系数，满意度≥50分时，系数1.0；40分≤满意度＜50分时，系数0.95；满意度＜40分时，系数0.9 | G8: 自建、外拓项目
A9: 6 | B9: 工程管控（20%） | C9: 设备设施管理 | D9: 0.1 | E9: 设施设备健康度R | F9: 设备设施健康度R为公区设备运行稳定性及预防性维护执行情况的综合得分，按各二级指标实际值折算后加权计算 | G9: 1、自建项目 2、设备设施健康度二级指标细则详见《品质服务检核计划》（附件三）
A10: 7 | C10: 自用能耗成本管控 | D10: 0.1 | E10: 自用水、电能耗实支成本管控 | F10: 自用能耗成本R以各公司上年度实际能耗成本支出为基准线： ①R≤25年实际成本，实际值较目标值每下降1%加1分（封顶120分），得分=100+(25年实际成本-R)/1%*1 ①R＞25年实际成本，实际值较目标值每上升1%减1分，得分=100+(R-25年实际成本)/1%*1 | G10: 自建项目
A11: 8 | B11: 效率管理(10%) | C11: 客户信息维护 | D11: 0.1 | E11: 客户基础信息准确率与400知晓率 | F11: 基础信息准确率基准线95%，400知晓率基准线50%，两项指标权重1:1 ①当R=基准线时，得100分 ②当R＞基准线时，较基准线每上升1%加2分(封顶120分)，得分=100+(R-基准线)/1%*2 ③当R＜基准线时，较基准线每下降1%减2分，得分=100-(基准线-R)/1%*2 | G11: 自建项目

Sheet 收费率
A2: 各城市公司当期收费率对比分析（综合）
A3: 公司 | B3: 45778 | C3: 46143 | E3: 公司 | F3: 得分 | G3: 权重得分 | I3: 公司 | J3: 考核指标 | L3: 验算
A4: 版纳 | B4: 0.48604382 | C4: 0.53657712 | D4: =C4-B4 -> 0.0505333 | E4: =A4 -> 版纳 | F4: =ROUND(IF(C4=J4,100,IF(AND(C4>J4),100+(C4-J4)/1%*3,IF(C4<J4,100+(C4-J4)/1%*2,100-(J4-C4)/1%*2))),1) -> 37.2 | G4: =F4*0.15 -> 5.58 | I4: 版纳 | J4: 0.85053911 | K4: =C4-J4 -> -0.31396199 | L4: =ROUND(100-(J4-C4)/1%*2,1) -> 37.2 | M4: =F4-L4 -> 0 | N4: 100-(基准线-R)/1%*2。
A5: 北城 | B5: 0.74257555 | C5: 0.73667093 | D5: =C5-B5 -> -0.0059046224 | E5: =A5 -> 北城 | F5: =ROUND(IF(C5=J5,100,IF(AND(C5>J5),100+(C5-J5)/1%*3,IF(C5<J5,100+(C5-J5)/1%*2,100-(J5-C5)/1%*2))),1) -> 74.8 | G5: =F5*0.15 -> 11.22 | I5: 北城 | J5: 0.86274859 | K5: =C5-J5 -> -0.12607766 | L5: =ROUND(100-(J5-C5)/1%*2,1) -> 74.8 | M5: =F5-L5 -> 0
A6: 北京 | B6: 0.7823668 | C6: 0.75335116 | D6: =C6-B6 -> -0.029015643 | E6: =A6 -> 北京 | F6: =ROUND(IF(C6=J6,100,IF(AND(C6>J6),100+(C6-J6)/1%*3,IF(C6<J6,100+(C6-J6)/1%*2,100-(J6-C6)/1%*2))),1) -> 67.2 | G6: =F6*0.15 -> 10.08 | I6: 北京 | J6: 0.91748947 | K6: =C6-J6 -> -0.16413831 | L6: =ROUND(100-(J6-C6)/1%*2,1) -> 67.2 | M6: =F6-L6 -> 0
A7: 滨湖 | B7: 0.77106781 | C7: 0.7346887 | D7: =C7-B7 -> -0.036379112 | E7: =A7 -> 滨湖 | F7: =ROUND(IF(C7=J7,100,IF(AND(C7>J7),100+(C7-J7)/1%*3,IF(C7<J7,100+(C7-J7)/1%*2,100-(J7-C7)/1%*2))),1) -> 63.9 | G7: =F7*0.15 -> 9.585 | I7: 滨湖 | J7: 0.91502025 | K7: =C7-J7 -> -0.18033155 | L7: =ROUND(100-(J7-C7)/1%*2,1) -> 63.9 | M7: =F7-L7 -> 0
A8: 阜阳 | B8: 0.71687304 | C8: 0.71014406 | D8: =C8-B8 -> -0.0067289844 | E8: 阜阳 | F8: =ROUND(IF(C8=J8,100,IF(AND(C8>J8),100+(C8-J8)/1%*3,IF(C8<J8,100+(C8-J8)/1%*2,100-(J8-C8)/1%*2))),1) -> 75.8 | G8: =F8*0.15 -> 11.37 | I8: 阜阳 | J8: 0.83110199 | K8: =C8-J8 -> -0.12095794 | L8: =ROUND(100-(J8-C8)/1%*2,1) -> 75.8 | M8: =F8-L8 -> 0
A9: 贵阳 | B9: 0.71831559 | C9: 0.71575907 | D9: =C9-B9 -> -0.0025565278 | E9: =A9 -> 贵阳 | F9: =ROUND(IF(C9=J9,100,IF(AND(C9>J9),100+(C9-J9)/1%*3,IF(C9<J9,100+(C9-J9)/1%*2,100-(J9-C9)/1%*2))),1) -> 64.5 | G9: =F9*0.15 -> 9.675 | I9: 贵阳 | J9: 0.89323852 | K9: =C9-J9 -> -0.17747946 | L9: =ROUND(100-(J9-C9)/1%*2,1) -> 64.5 | M9: =F9-L9 -> 0
A10: 昆明 | B10: 0.79752747 | C10: 0.81581077 | D10: =C10-B10 -> 0.018283305 | E10: =A10 -> 昆明 | F10: =ROUND(IF(C10=J10,100,IF(AND(C10>J10),100+(C10-J10)/1%*3,IF(C10<J10,100+(C10-J10)/1%*2,100-(J10-C10)/1%*2))),1) -> 74.9 | G10: =F10*0.15 -> 11.235 | I10: 昆明 | J10: 0.94130664 | K10: =C10-J10 -> -0.12549587 | L10: =ROUND(100-(J10-C10)/1%*2,1) -> 74.9 | M10: =F10-L10 -> 0
A11: 连江 | B11: 0.64032125 | C11: 0.64561217 | D11: =C11-B11 -> 0.0052909277 | E11: =A11 -> 连江 | F11: =ROUND(IF(C11=J11,100,IF(AND(C11>J11),100+(C11-J11)/1%*3,IF(C11<J11,100+(C11-J11)/1%*2,100-(J11-C11)/1%*2))),1) -> 65.1 | G11: =F11*0.15 -> 9.765 | I11: 连江 | J11: 0.82024414 | K11: =C11-J11 -> -0.17463196 | L11: =ROUND(100-(J11-C11)/1%*2,1) -> 65.1 | M11: =F11-L11 -> 0
A12: 罗源 | B12: 0.70266225 | C12: 0.74000209 | D12: =C12-B12 -> 0.037339845 | E12: =A12 -> 罗源 | F12: =ROUND(IF(C12=J12,100,IF(AND(C12>J12),100+(C12-J12)/1%*3,IF(C12<J12,100+(C12-J12)/1%*2,100-(J12-C12)/1%*2))),1) -> 78.1 | G12: =F12*0.15 -> 11.715 | I12: 罗源 | J12: 0.84925425 | K12: =C12-J12 -> -0.10925216 | L12: =ROUND(100-(J12-C12)/1%*2,1) -> 78.1 | M12: =F12-L12 -> 0
A13: 闽江 | B13: 0.73005613 | C13: 0.71301318 | D13: =C13-B13 -> -0.017042948 | E13: =A13 -> 闽江 | F13: =ROUND(IF(C13=J13,100,IF(AND(C13>J13),100+(C13-J13)/1%*3,IF(C13<J13,100+(C13-J13)/1%*2,100-(J13-C13)/1%*2))),1) -> 57.4 | G13: =F13*0.15 -> 8.61 | I13: 闽江 | J13: 0.92607614 | K13: =C13-J13 -> -0.21306296 | L13: =ROUND(100-(J13-C13)/1%*2,1) -> 57.4 | M13: =F13-L13 -> 0
A14: 宁波 | B14: 0.71309702 | C14: 0.66884709 | D14: =C14-B14 -> -0.044249933 | E14: =A14 -> 宁波 | F14: =ROUND(IF(C14=J14,100,IF(AND(C14>J14),100+(C14-J14)/1%*3,IF(C14<J14,100+(C14-J14)/1%*2,100-(J14-C14)/1%*2))),1) -> 55.8 | G14: =F14*0.15 -> 8.37 | I14: 宁波 | J14: 0.8899695 | K14: =C14-J14 -> -0.22112241 | L14: =ROUND(100-(J14-C14)/1%*2,1) -> 55.8 | M14: =F14-L14 -> 0
A15: 腾冲 | B15: 0.75899656 | C15: 0.7154912 | D15: =C15-B15 -> -0.043505362 | E15: =A15 -> 腾冲 | F15: =ROUND(IF(C15=J15,100,IF(AND(C15>J15),100+(C15-J15)/1%*3,IF(C15<J15,100+(C15-J15)/1%*2,100-(J15-C15)/1%*2))),1) -> 53 | G15: =F15*0.15 -> 7.95 | I15: 腾冲 | J15: 0.95070579 | K15: =C15-J15 -> -0.23521459 | L15: =ROUND(100-(J15-C15)/1%*2,1) -> 53 | M15: =F15-L15 -> 0
A16: 长沙 | B16: 0.64288745 | C16: 0.6936552 | D16: =C16-B16 -> 0.050767753 | E16: =A16 -> 长沙 | F16: =ROUND(IF(C16=J16,100,IF(AND(C16>J16),100+(C16-J16)/1%*3,IF(C16<J16,100+(C16-J16)/1%*2,100-(J16-C16)/1%*2))),1) -> 60 | G16: =F16*0.15 -> 9 | I16: 长沙 | J16: 0.89348274 | K16: =C16-J16 -> -0.19982754 | L16: =ROUND(100-(J16-C16)/1%*2,1) -> 60 | M16: =F16-L16 -> 0
A17: 合计 | B17: 0.72228792 | C17: 0.71845396 | D17: -0.0088836544 | I17: 集团 | J17: 0.89041041
A21: 各城市公司历欠收费率对比分析（综合)
A22: 公司 | B22: 45778 | C22: 46143 | E22: 公司 | F22: 得分 | G22: 权重得分 | I22: 公司 | J22: 考核指标 | L22: 验算
A23: 版纳 | B23: 0.16340834 | C23: 0.15092283 | D23: =C23-B23 -> -0.012485509 | E23: =A23 -> 版纳 | F23: =ROUND(IF(C23=J23,100,IF(AND(C23>J23),100+(C23-J23)/1%*3,IF(C23<J23,100+(C23-J23)/1%*2,100-(J23-C23)/1%*2))),1) -> 54.2 | G23: =F23*0.1 -> 5.42 | I23: 版纳 | J23: 0.37983292 | K23: =C23-J23 -> -0.22891009 | L23: =ROUND(100-(J23-C23)/1%*2,1) -> 54.2 | M23: =F23-L23 -> 0
A24: 北城 | B24: 0.20565772 | C24: 0.21689077 | D24: =C24-B24 -> 0.01123305 | E24: =A24 -> 北城 | F24: =ROUND(IF(C24=J24,100,IF(AND(C24>J24),100+(C24-J24)/1%*3,IF(C24<J24,100+(C24-J24)/1%*2,100-(J24-C24)/1%*2))),1) -> 47.9 | G24: =F24*0.1 -> 4.79 | I24: 北城 | J24: 0.47757673 | K24: =C24-J24 -> -0.26068597 | L24: =ROUND(100-(J24-C24)/1%*2,1) -> 47.9 | M24: =F24-L24 -> 0
A25: 北京 | B25: 0.14281271 | C25: 0.11719348 | D25: =C25-B25 -> -0.025619233 | E25: =A25 -> 北京 | F25: =ROUND(IF(C25=J25,100,IF(AND(C25>J25),100+(C25-J25)/1%*3,IF(C25<J25,100+(C25-J25)/1%*2,100-(J25-C25)/1%*2))),1) -> 53.8 | G25: =F25*0.1 -> 5.38 | I25: 北京 | J25: 0.34816798 | K25: =C25-J25 -> -0.23097451 | L25: =ROUND(100-(J25-C25)/1%*2,1) -> 53.8 | M25: =F25-L25 -> 0
A26: 滨湖 | B26: 0.28932089 | C26: 0.27902228 | D26: =C26-B26 -> -0.010298616 | E26: =A26 -> 滨湖 | F26: =ROUND(IF(C26=J26,100,IF(AND(C26>J26),100+(C26-J26)/1%*3,IF(C26<J26,100+(C26-J26)/1%*2,100-(J26-C26)/1%*2))),1) -> 34.9 | G26: =F26*0.1 -> 3.49 | I26: 滨湖 | J26: 0.60469842 | K26: =C26-J26 -> -0.32567615 | L26: =ROUND(100-(J26-C26)/1%*2,1) -> 34.9 | M26: =F26-L26 -> 0
A27: 阜阳 | B27: 0.37999294 | C27: 0.44431144 | D27: =C27-B27 -> 0.064318501 | E27: 阜阳 | F27: =ROUND(IF(C27=J27,100,IF(AND(C27>J27),100+(C27-J27)/1%*3,IF(C27<J27,100+(C27-J27)/1%*2,100-(J27-C27)/1%*2))),1) -> 68.4 | G27: =F27*0.1 -> 6.84 | I27: 阜阳 | J27: 0.60249489 | K27: =C27-J27 -> -0.15818345 | L27: =ROUND(100-(J27-C27)/1%*2,1) -> 68.4 | M27: =F27-L27 -> 0 | N27: 100-(基准线-R)/1%*3
A28: 贵阳 | B28: 0.14973326 | C28: 0.17035783 | D28: =C28-B28 -> 0.020624568 | E28: =A28 -> 贵阳 | F28: =ROUND(IF(C28=J28,100,IF(AND(C28>J28),100+(C28-J28)/1%*3,IF(C28<J28,100+(C28-J28)/1%*2,100-(J28-C28)/1%*2))),1) -> 50.5 | G28: =F28*0.1 -> 5.05 | I28: 贵阳 | J28: 0.41769932 | K28: =C28-J28 -> -0.24734149 | L28: =ROUND(100-(J28-C28)/1%*2,1) -> 50.5 | M28: =F28-L28 -> 0
A29: 昆明 | B29: 0.21340913 | C29: 0.16823656 | D29: =C29-B29 -> -0.04517257 | E29: =A29 -> 昆明 | F29: =ROUND(IF(C29=J29,100,IF(AND(C29>J29),100+(C29-J29)/1%*3,IF(C29<J29,100+(C29-J29)/1%*2,100-(J29-C29)/1%*2))),1) -> 62.9 | G29: =F29*0.1 -> 6.29 | I29: 昆明 | J29: 0.35364143 | K29: =C29-J29 -> -0.18540487 | L29: =ROUND(100-(J29-C29)/1%*2,1) -> 62.9 | M29: =F29-L29 -> 0
A30: 连江 | B30: 0.26404649 | C30: 0.21955233 | D30: =C30-B30 -> -0.044494164 | E30: =A30 -> 连江 | F30: =ROUND(IF(C30=J30,100,IF(AND(C30>J30),100+(C30-J30)/1%*3,IF(C30<J30,100+(C30-J30)/1%*2,100-(J30-C30)/1%*2))),1) -> 55 | G30: =F30*0.1 -> 5.5 | I30: 连江 | J30: 0.44431278 | K30: =C30-J30 -> -0.22476045 | L30: =ROUND(100-(J30-C30)/1%*2,1) -> 55 | M30: =F30-L30 -> 0
A31: 罗源 | B31: 0.51430032 | C31: 0.47244364 | D31: =C31-B31 -> -0.041856679 | E31: =A31 -> 罗源 | F31: =ROUND(IF(C31=J31,100,IF(AND(C31>J31),100+(C31-J31)/1%*3,IF(C31<J31,100+(C31-J31)/1%*2,100-(J31-C31)/1%*2))),1) -> 63.3 | G31: =F31*0.1 -> 6.33 | I31: 罗源 | J31: 0.65588217 | K31: =C31-J31 -> -0.18343853 | L31: =ROUND(100-(J31-C31)/1%*2,1) -> 63.3 | M31: =F31-L31 -> 0
A32: 闽江 | B32: 0.4373913 | C32: 0.40021356 | D32: =C32-B32 -> -0.037177742 | E32: =A32 -> 闽江 | F32: =ROUND(IF(C32=J32,100,IF(AND(C32>J32),100+(C32-J32)/1%*3,IF(C32<J32,100+(C32-J32)/1%*2,100-(J32-C32)/1%*2))),1) -> 52.2 | G32: =F32*0.1 -> 5.22 | I32: 闽江 | J32: 0.63897592 | K32: =C32-J32 -> -0.23876236 | L32: =ROUND(100-(J32-C32)/1%*2,1) -> 52.2 | M32: =F32-L32 -> 0
A33: 宁波 | B33: 0.24037867 | C33: 0.21861167 | D33: =C33-B33 -> -0.021767002 | E33: =A33 -> 宁波 | F33: =ROUND(IF(C33=J33,100,IF(AND(C33>J33),100+(C33-J33)/1%*3,IF(C33<J33,100+(C33-J33)/1%*2,100-(J33-C33)/1%*2))),1) -> 49 | G33: =F33*0.1 -> 4.9 | I33: 宁波 | J33: 0.47367945 | K33: =C33-J33 -> -0.25506779 | L33: =ROUND(100-(J33-C33)/1%*2,1) -> 49 | M33: =F33-L33 -> 0
A34: 腾冲 | B34: 0.13449113 | C34: 0.18110736 | D34: =C34-B34 -> 0.046616239 | E34: =A34 -> 腾冲 | F34: =ROUND(IF(C34=J34,100,IF(AND(C34>J34),100+(C34-J34)/1%*3,IF(C34<J34,100+(C34-J34)/1%*2,100-(J34-C34)/1%*2))),1) -> 67.6 | G34: =F34*0.1 -> 6.76 | I34: 腾冲 | J34: 0.3429118 | K34: =C34-J34 -> -0.16180443 | L34: =ROUND(100-(J34-C34)/1%*2,1) -> 67.6 | M34: =F34-L34 -> 0
A35: 长沙 | B35: 0.11707766 | C35: 0.087764015 | D35: =C35-B35 -> -0.02931365 | E35: =A35 -> 长沙 | F35: =ROUND(IF(C35=J35,100,IF(AND(C35>J35),100+(C35-J35)/1%*3,IF(C35<J35,100+(C35-J35)/1%*2,100-(J35-C35)/1%*2))),1) -> 63.9 | G35: =F35*0.1 -> 6.39 | I35: 长沙 | J35: 0.2680702 | K35: =C35-J35 -> -0.18030619 | L35: =ROUND(100-(J35-C35)/1%*2,1) -> 63.9 | M35: =F35-L35 -> 0
A36: 合计 | B36: 0.22567986 | C36: 0.2146522 | D36: -0.030425286 | I36: 集团 | J36: 0.44195012
B39: 自-应 | C39: 自-实 | D39: 外-应 | E39: 外-实 | F39: 25.5收费率 | H39: 自-应 | I39: 自-实 | J39: 外-应 | K39: 外-实 | L39: 26.5收费率
A40: 版纳 | B40: 1223.6354 | C40: 219.78919 | D40: 723.51885 | E40: 98.392052 | F40: =(C40+E40)/(B40+D40) -> 0.16340834 | H40: 1163.6342 | I40: 196.84716 | J40: 751.74287 | K40: 92.22697 | L40: =(I40+K40)/(H40+J40) -> 0.15092283
A41: 北城 | B41: 1330.6967 | C41: 329.16664 | D41: 1803.4308 | E41: 315.39086 | F41: =(C41+E41)/(B41+D41) -> 0.20565772 | H41: 1771.2507 | I41: 447.12236 | J41: 1791.2563 | K41: 325.55252 | L41: =(I41+K41)/(H41+J41) -> 0.21689077
A42: 北京 | B42: 1890.0047 | C42: 342.00474 | D42: 1884.7235 | E42: 197.07442 | F42: =(C42+E42)/(B42+D42) -> 0.14281271 | H42: 1701.9531 | I42: 263.91508 | J42: 1925.8214 | K42: 161.23643 | L42: =(I42+K42)/(H42+J42) -> 0.11719348
A43: 滨湖 | B43: 511.12055 | C43: 177.35 | D43: 519.88 | E43: 120.94 | F43: =(C43+E43)/(B43+D43) -> 0.28932089 | H43: 514.23007 | I43: 165.55042 | J43: 676.39322 | K43: 166.66 | L43: =(I43+K43)/(H43+J43) -> 0.27902228
A44: 阜阳 | B44: 316.54031 | C44: 112.28233 | D44: 403.62987 | E44: 161.37726 | F44: =(C44+E44)/(B44+D44) -> 0.37999294 | H44: 360.33473 | I44: 123.03304 | J44: 235.83292 | K44: 141.85107 | L44: =(I44+K44)/(H44+J44) -> 0.44431144
A45: 贵阳 | B45: 1848.7316 | C45: 253.63627 | D45: 1385.5667 | E45: 230.64577 | F45: =(C45+E45)/(B45+D45) -> 0.14973326 | H45: 2093.752 | I45: 443.20921 | J45: 1559.8275 | K45: 179.20665 | L45: =(I45+K45)/(H45+J45) -> 0.17035783
A46: 昆明 | B46: 287.12379 | C46: 124.30294 | D46: 1425.5469 | E46: 241.19662 | F46: =(C46+E46)/(B46+D46) -> 0.21340913 | H46: 269.51458 | I46: 108.03407 | J46: 1462.9497 | K46: 183.42977 | L46: =(I46+K46)/(H46+J46) -> 0.16823656
A47: 连江 | B47: 3845.99 | C47: 1016.38 | D47: 70.29 | E47: 17.7 | F47: =(C47+E47)/(B47+D47) -> 0.26404649 | H47: 4258.8 | I47: 934.51 | J47: 83.536082 | K47: 18.86 | L47: =(I47+K47)/(H47+J47) -> 0.21955233
A48: 罗源 | B48: 2395.1955 | C48: 1232.006 | D48: 7.92444 | E48: 3.919412 | F48: =(C48+E48)/(B48+D48) -> 0.51430032 | H48: 2472.8917 | I48: 1187.1489 | J48: 244.41361 | K48: 96.624745 | L48: =(I48+K48)/(H48+J48) -> 0.47244364
A49: 闽江 | B49: 414 | C49: 181.08 | D49: 0 | E49: 0 | F49: =(C49+E49)/(B49+D49) -> 0.4373913 | H49: 460.18 | I49: 213.672 | J49: 223.46 | K49: 59.93 | L49: =(I49+K49)/(H49+J49) -> 0.40021356
A50: 宁波 | B50: 1571.77 | C50: 413.95 | D50: 627.51 | E50: 114.71 | F50: =(C50+E50)/(B50+D50) -> 0.24037867 | H50: 2707.05 | I50: 656.4566 | J50: 319.12 | K50: 5.099464 | L50: =(I50+K50)/(H50+J50) -> 0.21861167
A51: 腾冲 | B51: 571.91669 | C51: 70.484219 | D51: 290.85919 | E51: 45.55148 | F51: =(C51+E51)/(B51+D51) -> 0.13449113 | H51: 627.34852 | I51: 94.162425 | J51: 164.58735 | K51: 49.262992 | L51: =(I51+K51)/(H51+J51) -> 0.18110736
A52: 长沙 | B52: 1525.6715 | C52: 202.55571 | D52: 1222.29 | E52: 119.16921 | F52: =(C52+E52)/(B52+D52) -> 0.11707766 | H52: 1559.8779 | I52: 167.27702 | J52: 1101.602 | K52: 66.305141 | L52: =(I52+K52)/(H52+J52) -> 0.087764015
A53: 合计 | B53: =SUM(B40:B52) -> 17732.397 | C53: =SUM(C40:C52) -> 4674.988 | D53: =SUM(D40:D52) -> 10365.17 | E53: =SUM(E40:E52) -> 1666.0671 | F53: =(C53+E53)/(B53+D53) -> 0.22567986 | H53: =SUM(H40:H52) -> 19960.818 | I53: =SUM(I40:I52) -> 5000.9383 | J53: =SUM(J40:J52) -> 10540.543 | K53: =SUM(K40:K52) -> 1546.2458 | L53: =(I53+K53)/(H53+J53) -> 0.2146522

Sheet 空间资源
A2: 公司 | B2: 空间资源指标 | C2: 已入账 | D2: 完成率 | E2: 目标完成率 | F2: 公司 | G2: 得分 | H2: 权重得分 | J2: 公司 | K2: 考核指标
A3: 版纳 | B3: 280.67058 | C3: 127.88337 | D3: =C3/B3 -> 0.45563511 | E3: 1 | F3: 版纳 | G3: =ROUND(IF(D3=$E$3,100,IF(AND(D3>$E$3),100+(D3-$E$3)/1%*3,100-($E$3-D3)/1%*2)),1) -> -8.9 | H3: =G3*0.1 -> -0.89 | J3: 版纳 | K3: 1
A4: 北城 | B4: 520.41069 | C4: 202.32602 | D4: =C4/B4 -> 0.38878145 | F4: 北城 | G4: =ROUND(IF(D4=$E$3,100,IF(AND(D4>$E$3),100+(D4-$E$3)/1%*3,100-($E$3-D4)/1%*2)),1) -> -22.2 | H4: =G4*0.1 -> -2.22 | J4: 北城 | K4: 1
A5: 北京 | B5: 1642.4747 | C5: 595.02894 | D5: =C5/B5 -> 0.36227586 | F5: 北京 | G5: =ROUND(IF(D5=$E$3,100,IF(AND(D5>$E$3),100+(D5-$E$3)/1%*3,100-($E$3-D5)/1%*2)),1) -> -27.5 | H5: =G5*0.1 -> -2.75 | J5: 北京 | K5: 1
A6: 滨湖 | B6: 505.97782 | C6: 220.90803 | D6: =C6/B6 -> 0.43659627 | F6: 滨湖 | G6: =ROUND(IF(D6=$E$3,100,IF(AND(D6>$E$3),100+(D6-$E$3)/1%*3,100-($E$3-D6)/1%*2)),1) -> -12.7 | H6: =G6*0.1 -> -1.27 | J6: 滨湖 | K6: 1
A7: 阜阳 | B7: 20.963642 | C7: 8.7150515 | D7: =C7/B7 -> 0.41572221 | F7: 阜阳 | G7: =ROUND(IF(D7=$E$3,100,IF(AND(D7>$E$3),100+(D7-$E$3)/1%*3,100-($E$3-D7)/1%*2)),1) -> -16.9 | H7: =G7*0.1 -> -1.69 | J7: 阜阳 | K7: 1
A8: 贵阳 | B8: 922.0172 | C8: 394.50547 | D8: =C8/B8 -> 0.42787213 | F8: 贵阳 | G8: =ROUND(IF(D8=$E$3,100,IF(AND(D8>$E$3),100+(D8-$E$3)/1%*3,100-($E$3-D8)/1%*2)),1) -> -14.4 | H8: =G8*0.1 -> -1.44 | J8: 贵阳 | K8: 1
A9: 昆明 | B9: 2112.0398 | C9: 795.00726 | D9: =C9/B9 -> 0.3764168 | F9: 昆明 | G9: =ROUND(IF(D9=$E$3,100,IF(AND(D9>$E$3),100+(D9-$E$3)/1%*3,100-($E$3-D9)/1%*2)),1) -> -24.7 | H9: =G9*0.1 -> -2.47 | J9: 昆明 | K9: 1
A10: 连江 | B10: 289.75328 | C10: 136.09906 | D10: =C10/B10 -> 0.4697067 | F10: 连江 | G10: =ROUND(IF(D10=$E$3,100,IF(AND(D10>$E$3),100+(D10-$E$3)/1%*3,100-($E$3-D10)/1%*2)),1) -> -6.1 | H10: =G10*0.1 -> -0.61 | J10: 连江 | K10: 1
A11: 罗源 | B11: 159.07708 | C11: 60.550383 | D11: =C11/B11 -> 0.38063549 | F11: 罗源 | G11: =ROUND(IF(D11=$E$3,100,IF(AND(D11>$E$3),100+(D11-$E$3)/1%*3,100-($E$3-D11)/1%*2)),1) -> -23.9 | H11: =G11*0.1 -> -2.39 | J11: 罗源 | K11: 1
A12: 闽江 | B12: 188.92003 | C12: 84.004721 | D12: =C12/B12 -> 0.44465756 | F12: 闽江 | G12: =ROUND(IF(D12=$E$3,100,IF(AND(D12>$E$3),100+(D12-$E$3)/1%*3,100-($E$3-D12)/1%*2)),1) -> -11.1 | H12: =G12*0.1 -> -1.11 | J12: 闽江 | K12: 1
A13: 宁波 | B13: 412.92583 | C13: 195.13466 | D13: =C13/B13 -> 0.47256589 | F13: 宁波 | G13: =ROUND(IF(D13=$E$3,100,IF(AND(D13>$E$3),100+(D13-$E$3)/1%*3,100-($E$3-D13)/1%*2)),1) -> -5.5 | H13: =G13*0.1 -> -0.55 | J13: 宁波 | K13: 1
A14: 腾冲 | B14: 121.09677 | C14: 74.556415 | D14: =C14/B14 -> 0.61567635 | F14: 腾冲 | G14: =ROUND(IF(D14=$E$3,100,IF(AND(D14>$E$3),100+(D14-$E$3)/1%*3,100-($E$3-D14)/1%*2)),1) -> 23.1 | H14: =G14*0.1 -> 2.31 | J14: 腾冲 | K14: 1
A15: 长沙 | B15: 661.0042 | C15: 222.49288 | D15: =C15/B15 -> 0.33659829 | F15: 长沙 | G15: =ROUND(IF(D15=$E$3,100,IF(AND(D15>$E$3),100+(D15-$E$3)/1%*3,100-($E$3-D15)/1%*2)),1) -> -32.7 | H15: =G15*0.1 -> -3.27 | J15: 长沙 | K15: 1
A16: 合计 | B16: 7837.3316 | C16: =SUM(C3:C15) -> 3117.2123 | D16: =C16/B16 -> 0.39773898
A20: 公司 | B20: 25年完成 | C20: 26年预算 | D20: 孰高指标 | E20: 已入账 | F20: 入账同比 | G20: 待入账 | H20: 待续签 | I20: 全年预估收入 | J20: 业绩缺口 | K20: 4月缺口 | L20: 较上月新增 | M20: 备注
A21: 阜阳 | B21: 20.963642 | C21: 20.412388 | D21: 20.963642 | E21: 8.7150515 | F21: 2.1763707 | G21: 5.38 | H21: 7 | I21: =E21+G21+H21 -> 21.095051 | J21: =E21+G21+H21-D21 -> 0.1314098 | K21: 0.21275665 | L21: =-K21+J21 -> -0.08134685
A22: 北城 | B22: 520.41069 | C22: 396.09429 | D22: 520.41069 | E22: 202.32602 | F22: 10.988084 | G22: 170.45 | H22: 99 | I22: =E22+G22+H22 -> 471.77602 | J22: =E22+G22+H22-D22 -> -48.63467 | K22: -50.49825 | L22: =-K22+J22 -> 1.8635805
A23: 宁波 | B23: 412.92583 | C23: 392.40341 | D23: 412.92583 | E23: 195.13466 | F23: 29.475473 | G23: 149.9 | H23: 50 | I23: =E23+G23+H23 -> 395.03466 | J23: =E23+G23+H23-D23 -> -17.891171 | K23: -55.292366 | L23: =-K23+J23 -> 37.401195
A24: 滨湖 | B24: 505.97782 | C24: 501.99821 | D24: =693.97782195-188 -> 505.97782 | E24: 220.90803 | F24: 17.238108 | G24: 144.01 | H24: 15 | I24: =E24+G24+H24 -> 379.91803 | J24: =E24+G24+H24-D24 -> -126.05979 | K24: -123.25837 | L24: =-K24+J24 -> -2.8014205 | M24: 1个广告合同提前退租，替换商家协商中
A25: 长沙 | B25: 614.49592 | C25: 661.0042 | D25: 661.0042 | E25: 222.49288 | F25: -22.594008 | G25: 274.78502 | H25: 31.78 | I25: =E25+G25+H25 -> 529.0579 | J25: =E25+G25+H25-D25 -> -131.94629 | K25: -137.49695 | L25: =-K25+J25 -> 5.5506528
A26: 贵阳 | B26: 922.0172 | C26: 810.02518 | D26: 922.0172 | E26: 394.50547 | F26: -25.412295 | G26: 301.77 | H26: 76.94 | I26: =E26+G26+H26 -> 773.21547 | J26: =E26+G26+H26-D26 -> -148.80174 | K26: -203.74319 | L26: =-K26+J26 -> 54.941453
A27: 北京 | B27: 1642.4747 | C27: 1562.0577 | D27: 1642.4747 | E27: 595.02894 | F27: -56.285752 | G27: 602.54487 | H27: 236.96338 | I27: =E27+G27+H27 -> 1434.5372 | J27: =E27+G27+H27-D27 -> -207.93751 | K27: -207.32784 | L27: =-K27+J27 -> -0.60967052 | M27: 电梯广告退租
A28: 小计 | B28: =SUM(B21:B27) -> 4639.2658 | C28: =SUM(C21:C27) -> 4343.9954 | D28: =SUM(D21:D27) -> 4685.7741 | E28: =SUM(E21:E27) -> 1839.1111 | F28: =SUM(F21:F27) -> -44.414019 | G28: =SUM(G21:G27) -> 1648.8399 | H28: =SUM(H21:H27) -> 516.68338 | I28: =SUM(I21:I27) -> 4004.6343 | ... K28: =SUM(K21:K27) -> -777.40421 | L28: =-K28+J28 -> 96.264444
A29: 闽江 | B29: 188.92003 | C29: 152 | D29: 188.92003 | E29: 84.004721 | F29: 1.8707083 | G29: 93.37 | H29: 6.94 | I29: =E29+G29+H29 -> 184.31472 | J29: =E29+G29+H29-D29 -> -4.6053102 | K29: -3.8464132 | L29: =-K29+J29 -> -0.75889695
A30: 腾冲 | B30: 121.09677 | C30: 100.25263 | D30: 121.09677 | E30: 74.556415 | F30: 29.055305 | G30: 15.585824 | H30: 5 | I30: =E30+G30+H30 -> 95.14224 | J30: =E30+G30+H30-D30 -> -25.954527 | K30: -34.072877 | L30: =-K30+J30 -> 8.1183496
A31: 罗源 | B31: 159.07708 | C31: 115.44343 | D31: 159.07708 | E31: 60.550383 | F31: -3.9209268 | G31: 42.325593 | H31: 9.42 | I31: =E31+G31+H31 -> 112.29598 | J31: =E31+G31+H31-D31 -> -46.781104 | K31: -56.63476 | L31: =-K31+J31 -> 9.8536556
A32: 连江 | B32: 289.75328 | C32: 193 | D32: 289.75328 | E32: 136.09906 | F32: 23.427445 | G32: 93.13 | H32: 7.08 | I32: =E32+G32+H32 -> 236.30906 | J32: =E32+G32+H32-D32 -> -53.444223 | K32: -53.44345 | L32: =-K32+J32 -> -0.00077255 | M32: 5月签约合同已计入4月
A33: 版纳 | B33: 280.67058 | C33: 239.48988 | D33: 280.67058 | E33: 127.88337 | F33: 33.48674 | G33: 94.1 | H33: 3.14 | I33: =E33+G33+H33 -> 225.12337 | J33: =E33+G33+H33-D33 -> -55.547208 | K33: -57.410315 | L33: =-K33+J33 -> 1.8631064
A34: 昆明 | B34: 2093.8022 | C34: 2112.0398 | D34: 2112.0398 | E34: 795.00726 | F34: -3.5485747 | G34: 720 | H34: 375 | I34: =E34+G34+H34 -> 1890.0073 | J34: =E34+G34+H34-D34 -> -222.0325 | K34: -218.24542 | L34: =-K34+J34 -> -3.787078 | M34: 2个合同退租，26年金额6.5万
A35: 小计 | B35: =SUM(B29:B34) -> 3133.32 | C35: =SUM(C29:C34) -> 2912.2257 | D35: =SUM(D29:D34) -> 3151.5575 | E35: =SUM(E29:E34) -> 1278.1012 | F35: =SUM(F29:F34) -> 80.370696 | G35: =SUM(G29:G34) -> 1058.5114 | H35: =SUM(H29:H34) -> 406.58 | I35: =SUM(I29:I34) -> 2743.1926 | ... K35: =SUM(K29:K34) -> -423.65324 | L35: =-K35+J35 -> 15.288364
A36: 合计 | B36: =B28+B35 -> 7772.5858 | C36: =C28+C35 -> 7256.2211 | D36: =D28+D35 -> 7837.3316 | E36: =E28+E35 -> 3117.2123 | F36: =F28+F35 -> 35.956677 | G36: =G28+G35 -> 2707.3513 | H36: =H28+H35 -> 923.26338 | I36: =I28+I35 -> 6747.8269 | ... K36: =K28+K35 -> -1201.0575 | L36: =-K36+J36 -> 111.55281
A40: 公司 | B40: 已入账 | C40: 待入账 | D40: 待续签 | E40: 业绩缺口 | F40: 全年预估收入
A41: 昆明 | B41: =VLOOKUP($A41,$A$21:$J$34,5,0) -> 795.00726 | C41: =VLOOKUP($A41,$A$21:$J$34,7,0) -> 720 | D41: =VLOOKUP($A41,$A$21:$J$34,8,0) -> 375 | E41: =IF(J21<0,VLOOKUP($A41,$A$21:$J$34,10,0)*(-1),VLOOKUP($A41,$A$21:$J$34,10,0)) -> -222.0325 | F41: =B41+C41+D41 -> 1890.0073
A42: 北京 | B42: =VLOOKUP($A42,$A$21:$J$34,5,0) -> 595.02894 | C42: =VLOOKUP($A42,$A$21:$J$34,5,0) -> 595.02894 | D42: =VLOOKUP($A42,$A$21:$J$34,5,0) -> 595.02894 | E42: =IF(J22<0,VLOOKUP($A42,$A$21:$J$34,10,0)*(-1),VLOOKUP($A42,$A$21:$J$34,10,0)) -> 207.93751 | F42: =B42+C42+D42 -> 1785.0868
A43: 贵阳 | B43: =VLOOKUP($A43,$A$21:$J$34,5,0) -> 394.50547 | C43: =VLOOKUP($A43,$A$21:$J$34,5,0) -> 394.50547 | D43: =VLOOKUP($A43,$A$21:$J$34,5,0) -> 394.50547 | E43: =IF(J23<0,VLOOKUP($A43,$A$21:$J$34,10,0)*(-1),VLOOKUP($A43,$A$21:$J$34,10,0)) -> 148.80174 | F43: =B43+C43+D43 -> 1183.5164
A44: 长沙 | B44: =VLOOKUP($A44,$A$21:$J$34,5,0) -> 222.49288 | C44: =VLOOKUP($A44,$A$21:$J$34,5,0) -> 222.49288 | D44: =VLOOKUP($A44,$A$21:$J$34,5,0) -> 222.49288 | E44: =IF(J24<0,VLOOKUP($A44,$A$21:$J$34,10,0)*(-1),VLOOKUP($A44,$A$21:$J$34,10,0)) -> 131.94629 | F44: =B44+C44+D44 -> 667.47864
A45: 滨湖 | B45: =VLOOKUP($A45,$A$21:$J$34,5,0) -> 220.90803 | C45: =VLOOKUP($A45,$A$21:$J$34,5,0) -> 220.90803 | D45: =VLOOKUP($A45,$A$21:$J$34,5,0) -> 220.90803 | E45: =IF(J25<0,VLOOKUP($A45,$A$21:$J$34,10,0)*(-1),VLOOKUP($A45,$A$21:$J$34,10,0)) -> 126.05979 | F45: =B45+C45+D45 -> 662.72409
A46: 北城 | B46: =VLOOKUP($A46,$A$21:$J$34,5,0) -> 202.32602 | C46: =VLOOKUP($A46,$A$21:$J$34,5,0) -> 202.32602 | D46: =VLOOKUP($A46,$A$21:$J$34,5,0) -> 202.32602 | E46: =IF(J26<0,VLOOKUP($A46,$A$21:$J$34,10,0)*(-1),VLOOKUP($A46,$A$21:$J$34,10,0)) -> 48.63467 | F46: =B46+C46+D46 -> 606.97806
A47: 宁波 | B47: =VLOOKUP($A47,$A$21:$J$34,5,0) -> 195.13466 | C47: =VLOOKUP($A47,$A$21:$J$34,5,0) -> 195.13466 | D47: =VLOOKUP($A47,$A$21:$J$34,5,0) -> 195.13466 | E47: =IF(J27<0,VLOOKUP($A47,$A$21:$J$34,10,0)*(-1),VLOOKUP($A47,$A$21:$J$34,10,0)) -> 17.891171 | F47: =B47+C47+D47 -> 585.40399
A48: 连江 | B48: =VLOOKUP($A48,$A$21:$J$34,5,0) -> 136.09906 | C48: =VLOOKUP($A48,$A$21:$J$34,5,0) -> 136.09906 | D48: =VLOOKUP($A48,$A$21:$J$34,5,0) -> 136.09906 | E48: =IF(J28<0,VLOOKUP($A48,$A$21:$J$34,10,0)*(-1),VLOOKUP($A48,$A$21:$J$34,10,0)) -> 53.444223 | F48: =B48+C48+D48 -> 408.29717
A49: 版纳 | B49: =VLOOKUP($A49,$A$21:$J$34,5,0) -> 127.88337 | C49: =VLOOKUP($A49,$A$21:$J$34,5,0) -> 127.88337 | D49: =VLOOKUP($A49,$A$21:$J$34,5,0) -> 127.88337 | E49: =IF(J29<0,VLOOKUP($A49,$A$21:$J$34,10,0)*(-1),VLOOKUP($A49,$A$21:$J$34,10,0)) -> 55.547208 | F49: =B49+C49+D49 -> 383.6501
A50: 闽江 | B50: =VLOOKUP($A50,$A$21:$J$34,5,0) -> 84.004721 | C50: =VLOOKUP($A50,$A$21:$J$34,5,0) -> 84.004721 | D50: =VLOOKUP($A50,$A$21:$J$34,5,0) -> 84.004721 | E50: =IF(J30<0,VLOOKUP($A50,$A$21:$J$34,10,0)*(-1),VLOOKUP($A50,$A$21:$J$34,10,0)) -> 4.6053102 | F50: =B50+C50+D50 -> 252.01416
A51: 腾冲 | B51: =VLOOKUP($A51,$A$21:$J$34,5,0) -> 74.556415 | C51: =VLOOKUP($A51,$A$21:$J$34,5,0) -> 74.556415 | D51: =VLOOKUP($A51,$A$21:$J$34,5,0) -> 74.556415 | E51: =IF(J31<0,VLOOKUP($A51,$A$21:$J$34,10,0)*(-1),VLOOKUP($A51,$A$21:$J$34,10,0)) -> 25.954527 | F51: =B51+C51+D51 -> 223.66925
A52: 罗源 | B52: =VLOOKUP($A52,$A$21:$J$34,5,0) -> 60.550383 | C52: =VLOOKUP($A52,$A$21:$J$34,5,0) -> 60.550383 | D52: =VLOOKUP($A52,$A$21:$J$34,5,0) -> 60.550383 | E52: =IF(J32<0,VLOOKUP($A52,$A$21:$J$34,10,0)*(-1),VLOOKUP($A52,$A$21:$J$34,10,0)) -> 46.781104 | F52: =B52+C52+D52 -> 181.65115
A53: 阜阳 | B53: =VLOOKUP($A53,$A$21:$J$34,5,0) -> 8.7150515 | C53: =VLOOKUP($A53,$A$21:$J$34,5,0) -> 8.7150515 | D53: =VLOOKUP($A53,$A$21:$J$34,5,0) -> 8.7150515 | E53: =IF(J33<0,VLOOKUP($A53,$A$21:$J$34,10,0)*(-1),VLOOKUP($A53,$A$21:$J$34,10,0)) -> -0.1314098 | F53: =B53+C53+D53 -> 26.145154
A54: 合计 | B54: =SUM(B41:B53) -> 3117.2123 | C54: =SUM(C41:C53) -> 3042.205 | D54: =SUM(D41:D53) -> 2697.205 | E54: =SUM(E41:E53) -> 645.43964 | F54: =SUM(F41:F53) -> 8856.6223

Sheet 业主满意度
A2: 2026年自建项目业主满意度
A3: 公司 | B3: 自调问卷 | C3: 400电话调查 | D3: 问卷8:电话2 | E3: 问卷7:电话3 | F3: 问卷6:电话4 | H3: 公司 | I3: 满意度 | J3: 得分 | K3: 权重得分
A4: 版纳 | H4: 版纳 | I4: =D4 -> 0 | J4: =ROUND(IF(I4=92%,100,IF(I4>92%,100+(I4-92%)/1%*5,IF(AND(I4>82%,I4<92%),100-(92%-I4)/1%*3,70))),1) -> 70 | K4: =ROUND(J4*0.25,1) -> 17.5
A5: 北城 | H5: 北城 | I5: =D5 -> 0 | J5: =ROUND(IF(I5=92%,100,IF(I5>92%,100+(I5-92%)/1%*5,IF(AND(I5>82%,I5<92%),100-(92%-I5)/1%*3,70))),1) -> 70 | K5: =ROUND(J5*0.25,1) -> 17.5
A6: 北京 | H6: 北京 | I6: =D6 -> 0 | J6: =ROUND(IF(I6=92%,100,IF(I6>92%,100+(I6-92%)/1%*5,IF(AND(I6>82%,I6<92%),100-(92%-I6)/1%*3,70))),1) -> 70 | K6: =ROUND(J6*0.25,1) -> 17.5
A7: 滨湖 | H7: 滨湖 | I7: =D7 -> 0 | J7: =ROUND(IF(I7=92%,100,IF(I7>92%,100+(I7-92%)/1%*5,IF(AND(I7>82%,I7<92%),100-(92%-I7)/1%*3,70))),1) -> 70 | K7: =ROUND(J7*0.25,1) -> 17.5
A8: 阜阳 | H8: 阜阳 | I8: =D8 -> 0 | J8: =ROUND(IF(I8=92%,100,IF(I8>92%,100+(I8-92%)/1%*5,IF(AND(I8>82%,I8<92%),100-(92%-I8)/1%*3,70))),1) -> 70 | K8: =ROUND(J8*0.25,1) -> 17.5
A9: 贵阳 | H9: 贵阳 | I9: =D9 -> 0 | J9: =ROUND(IF(I9=92%,100,IF(I9>92%,100+(I9-92%)/1%*5,IF(AND(I9>82%,I9<92%),100-(92%-I9)/1%*3,70))),1) -> 70 | K9: =ROUND(J9*0.25,1) -> 17.5
A10: 昆明 | H10: 昆明 | I10: =D10 -> 0 | J10: =ROUND(IF(I10=92%,100,IF(I10>92%,100+(I10-92%)/1%*5,IF(AND(I10>82%,I10<92%),100-(92%-I10)/1%*3,70))),1) -> 70 | K10: =ROUND(J10*0.25,1) -> 17.5
A11: 连江 | H11: 连江 | I11: =D11 -> 0 | J11: =ROUND(IF(I11=92%,100,IF(I11>92%,100+(I11-92%)/1%*5,IF(AND(I11>82%,I11<92%),100-(92%-I11)/1%*3,70))),1) -> 70 | K11: =ROUND(J11*0.25,1) -> 17.5
A12: 罗源 | H12: 罗源 | I12: =D12 -> 0 | J12: =ROUND(IF(I12=92%,100,IF(I12>92%,100+(I12-92%)/1%*5,IF(AND(I12>82%,I12<92%),100-(92%-I12)/1%*3,70))),1) -> 70 | K12: =ROUND(J12*0.25,1) -> 17.5
A13: 闽江 | H13: 闽江 | I13: =D13 -> 0 | J13: =ROUND(IF(I13=92%,100,IF(I13>92%,100+(I13-92%)/1%*5,IF(AND(I13>82%,I13<92%),100-(92%-I13)/1%*3,70))),1) -> 70 | K13: =ROUND(J13*0.25,1) -> 17.5
A14: 宁波 | H14: 宁波 | I14: =D14 -> 0 | J14: =ROUND(IF(I14=92%,100,IF(I14>92%,100+(I14-92%)/1%*5,IF(AND(I14>82%,I14<92%),100-(92%-I14)/1%*3,70))),1) -> 70 | K14: =ROUND(J14*0.25,1) -> 17.5
A15: 腾冲 | H15: 腾冲 | I15: =D15 -> 0 | J15: =ROUND(IF(I15=92%,100,IF(I15>92%,100+(I15-92%)/1%*5,IF(AND(I15>82%,I15<92%),100-(92%-I15)/1%*3,70))),1) -> 70 | K15: =ROUND(J15*0.25,1) -> 17.5
... A17: 合计 | H17: 合计 | I17: =D17 -> 0 | J17: =ROUND(IF(I17=92%,100,IF(I17>92%,100+(I17-92%)/1%*5,IF(AND(I17>82%,I17<92%),100-(92%-I17)/1%*3,70))),1) -> 70 | K17: =ROUND(J17*0.25,1) -> 17.5
A20: 公司 | B20: 异常问卷 | C20: 问卷有效率 | D20: 扣罚金额 | E20: 扣罚星级
A21: 宁波
A22: 北城
A23: 贵阳
A24: 滨湖
A25: 罗源
A26: 连江
A27: 昆明
A28: 长沙
A29: 版纳
A30: 北京
A31: 闽江
A32: 阜阳
... A34: 总计

Sheet 投诉完成率
A2: 投诉完成率=（本月办结总单量+上月未办结单量-本月不满意单量-上月转本月办结不满意单量）/（投诉总单量+上月未办结单量）
A3: 2026年投诉完成率（数据为呼叫中心提供）
A4: 公司 | B4: 1月 | C4: 2月 | D4: 3月 | E4: 4月 | F4: 5月 | G4: 6月 | H4: 7月 | I4: 8月 | J4: 9月 | K4: 10月 | L4: 11月 | M4: 12月 | O4: 公司 | P4: 得分 | Q4: 权重得分 | S4: 年度满意度 | T4: 系数
A5: 版纳 | B5: 0.56930693 | C5: 0.64761905 | D5: 0.74324324 | E5: 0.80291971 | F5: 0.6557377 | N5: =AVERAGE(B5:M5) -> 0.68376533 | O5: =A5 -> 版纳 | P5: =(100-COUNTIF(B5:M5,"<0.75")*5)*T5 -> 80 | Q5: =P5*0.1 -> 8 | S5: =N115 -> 56.104418 | T5: =IF(S5>50,1,IF(S5<40,0.9,0.95)) -> 1 | U5: =IF(S2="","",IF(S2>=50,1,IF(S2<40,0.9,0.95)))
A6: 北城 | B6: 0.81533101 | C6: 0.73577236 | D6: 0.79661017 | E6: 0.75636364 | F6: 0.73782772 | N6: =AVERAGE(B6:M6) -> 0.76838098 | O6: =A6 -> 北城 | P6: =(100-COUNTIF(B6:M6,"<0.75")*5)*T6 -> 90 | Q6: =P6*0.1 -> 9 | S6: =N116 -> 51.604938 | T6: =IF(S6>50,1,IF(S6<40,0.9,0.95)) -> 1
A7: 北京 | B7: 0.73263889 | C7: 0.79638009 | D7: 0.47906977 | E7: 0.65145228 | F7: 0.52091255 | N7: =AVERAGE(B7:M7) -> 0.63609072 | O7: =A7 -> 北京 | P7: =(100-COUNTIF(B7:M7,"<0.75")*5)*T7 -> 80 | Q7: =P7*0.1 -> 8 | S7: =N117 -> 60.640569 | T7: =IF(S7>50,1,IF(S7<40,0.9,0.95)) -> 1
A8: 滨湖 | B8: 0.68312757 | C8: 0.7189781 | D8: 0.68441065 | E8: 0.75268817 | F8: 0.79710145 | N8: =AVERAGE(B8:M8) -> 0.72726119 | O8: =A8 -> 滨湖 | P8: =(100-COUNTIF(B8:M8,"<0.75")*5)*T8 -> 85 | Q8: =P8*0.1 -> 8.5 | S8: =N118 -> 51.279318 | T8: =IF(S8>50,1,IF(S8<40,0.9,0.95)) -> 1
A9: 阜阳 | B9: 0.46835443 | C9: 0.79166667 | D9: 0.47368421 | E9: 0.67142857 | F9: 0.84782609 | N9: =AVERAGE(B9:M9) -> 0.65059199 | O9: 阜阳 | P9: =(100-COUNTIF(B9:M9,"<0.75")*5)*T9 -> 80.75 | Q9: =P9*0.1 -> 8.075 | S9: =N119 -> 46.55914 | T9: =IF(S9>50,1,IF(S9<40,0.9,0.95)) -> 0.95
A10: 贵阳 | B10: 0.824 | C10: 0.88023952 | D10: 0.91219512 | E10: 0.84210526 | F10: 0.87109375 | N10: =AVERAGE(B10:M10) -> 0.86592673 | O10: =A10 -> 贵阳 | P10: =(100-COUNTIF(B10:M10,"<0.75")*5)*T10 -> 100 | Q10: =P10*0.1 -> 10 | S10: =N120 -> 74.830508 | T10: =IF(S10>50,1,IF(S10<40,0.9,0.95)) -> 1
A11: 昆明 | B11: 0.70562771 | C11: 0.855 | D11: 0.89400922 | E11: 0.91176471 | F11: 0.836 | N11: =AVERAGE(B11:M11) -> 0.84048033 | O11: =A11 -> 昆明 | P11: =(100-COUNTIF(B11:M11,"<0.75")*5)*T11 -> 95 | Q11: =P11*0.1 -> 9.5 | S11: =N121 -> 75.048544 | T11: =IF(S11>50,1,IF(S11<40,0.9,0.95)) -> 1
A12: 连江 | B12: 0.75 | C12: 0.76727273 | D12: 0.74895397 | E12: 0.83557951 | F12: 0.7748538 | N12: =AVERAGE(B12:M12) -> 0.775332 | O12: =A12 -> 连江 | P12: =(100-COUNTIF(B12:M12,"<0.75")*5)*T12 -> 95 | Q12: =P12*0.1 -> 9.5 | S12: =N122 -> 52.545045 | T12: =IF(S12>50,1,IF(S12<40,0.9,0.95)) -> 1
A13: 罗源 | B13: 0.57768924 | C13: 0.63513514 | D13: 0.57831325 | E13: 0.56065574 | F13: 0.64575646 | N13: =AVERAGE(B13:M13) -> 0.59950997 | O13: =A13 -> 罗源 | P13: =(100-COUNTIF(B13:M13,"<0.75")*5)*T13 -> 67.5 | Q13: =P13*0.1 -> 6.75 | S13: =N123 -> 33.677249 | T13: =IF(S13>50,1,IF(S13<40,0.9,0.95)) -> 0.9
A14: 闽江 | B14: 0.77941176 | C14: 0.82608696 | D14: 0.83076923 | E14: 0.81690141 | F14: 0.82692308 | N14: =AVERAGE(B14:M14) -> 0.81601849 | O14: =A14 -> 闽江 | P14: =(100-COUNTIF(B14:M14,"<0.75")*5)*T14 -> 100 | Q14: =P14*0.1 -> 10 | S14: =N124 -> 63.723404 | T14: =IF(S14>50,1,IF(S14<40,0.9,0.95)) -> 1
A15: 宁波 | B15: 0.71641791 | C15: 0.6993007 | D15: 0.70604396 | E15: 0.718 | F15: 0.75592417 | N15: =AVERAGE(B15:M15) -> 0.71913735 | O15: =A15 -> 宁波 | P15: =(100-COUNTIF(B15:M15,"<0.75")*5)*T15 -> 80 | Q15: =P15*0.1 -> 8 | S15: =N125 -> 57.215815 | T15: =IF(S15>50,1,IF(S15<40,0.9,0.95)) -> 1
A16: 腾冲 | B16: 0.90625 | C16: 0.75862069 | D16: 0.7 | E16: 0.36956522 | F16: 0.75757576 | N16: =AVERAGE(B16:M16) -> 0.69840233 | O16: =A16 -> 腾冲 | P16: =(100-COUNTIF(B16:M16,"<0.75")*5)*T16 -> 81 | Q16: =P16*0.1 -> 8.1 | S16: =N126 -> 34.770642 | T16: =IF(S16>50,1,IF(S16<40,0.9,0.95)) -> 0.9
A17: 长沙 | B17: 0.61983471 | C17: 0.8 | D17: 0.81621622 | E17: 0.74208145 | F17: 0.77731092 | N17: =AVERAGE(B17:M17) -> 0.75108866 | O17: =A17 -> 长沙 | P17: =(100-COUNTIF(B17:M17,"<0.75")*5)*T17 -> 90 | Q17: =P17*0.1 -> 9 | S17: =N127 -> 56.412698 | T17: =IF(S17>50,1,IF(S17<40,0.9,0.95)) -> 1
A18: 合计 | B18: 0.70362694 | C18: 0.74979184 | D18: 0.72790507 | E18: 0.73548171 | F18: 0.7460815 | N18: =AVERAGE(B18:M18) -> 0.73257741
A21: 2026投诉汇总
A22: 公司 | B22: 1月 | C22: 2月 | D22: 3月 | E22: 4月 | F22: 5月 | G22: 6月 | H22: 7月 | I22: 8月 | J22: 9月 | K22: 10月 | L22: 11月 | M22: 12月 | N22: 总计
A23: 版纳 | B23: 202 | C23: 210 | D23: 147 | E23: 136 | F23: 121 | N23: =SUM(B23:M23) -> 816
A24: 北城 | B24: 286 | C24: 245 | D24: 236 | E24: 275 | F24: 267 | N24: =SUM(B24:M24) -> 1309
A25: 北京 | B25: 287 | C25: 221 | D25: 214 | E25: 215 | F25: 213 | N25: =SUM(B25:M25) -> 1150
A26: 滨湖 | B26: 243 | C26: 274 | D26: 263 | E26: 279 | F26: 274 | N26: =SUM(B26:M26) -> 1333
A27: 阜阳 | B27: 79 | C27: 48 | D27: 38 | E27: 70 | F27: 46 | N27: =SUM(B27:M27) -> 281
A28: 贵阳 | B28: 250 | C28: 167 | D28: 205 | E28: 247 | F28: 256 | N28: =SUM(B28:M28) -> 1125
A29: 昆明 | B29: 229 | C29: 200 | D29: 217 | E29: 170 | F29: 250 | N29: =SUM(B29:M29) -> 1066
A30: 连江 | B30: 320 | C30: 275 | D30: 239 | E30: 371 | F30: 342 | N30: =SUM(B30:M30) -> 1547
A31: 罗源 | B31: 234 | C31: 205 | D31: 246 | E31: 294 | F31: 247 | N31: =SUM(B31:M31) -> 1226
A32: 闽江 | B32: 68 | C32: 69 | D32: 65 | E32: 71 | F32: 50 | N32: =SUM(B32:M32) -> 323
A33: 宁波 | B33: 396 | C33: 281 | D33: 353 | E33: 489 | F33: 412 | N33: =SUM(B33:M33) -> 1931
A34: 腾冲 | B34: 32 | C34: 29 | D34: 20 | E34: 92 | F34: 66 | N34: =SUM(B34:M34) -> 239
A35: 长沙 | B35: 242 | C35: 155 | D35: 185 | E35: 221 | F35: 238 | N35: =SUM(B35:M35) -> 1041
A36: 总计 | B36: =SUM(B23:B35) -> 2868 | C36: =SUM(C23:C35) -> 2379 | D36: =SUM(D23:D35) -> 2428 | E36: =SUM(E23:E35) -> 2930 | F36: =SUM(F23:F35) -> 2782 | G36: =SUM(G23:G35) -> 0 | H36: =SUM(H23:H35) -> 0 | I36: =SUM(I23:I35) -> 0 | ... M36: =SUM(M23:M35) -> 0 | N36: =SUM(B36:M36) -> 13387
A39: 2026投诉回访不满意工单
A40: 公司 | B40: 1月 | C40: 2月 | D40: 3月 | E40: 4月 | F40: 5月 | G40: 6月 | H40: 7月 | I40: 8月 | J40: 9月 | K40: 10月 | L40: 11月 | M40: 12月 | N40: 总计
A41: 版纳 | B41: 57 | C41: 55 | D41: 32 | E41: 22 | F41: 24 | N41: =SUM(B41:M41) -> 190
A42: 北城 | B42: 49 | C42: 64 | D42: 48 | E42: 65 | F42: 70 | N42: =SUM(B42:M42) -> 296
A43: 北京 | B43: 51 | C43: 33 | D43: 41 | E43: 28 | F43: 28 | N43: =SUM(B43:M43) -> 181
A44: 滨湖 | B44: 77 | C44: 76 | D44: 83 | E44: 67 | F44: 54 | N44: =SUM(B44:M44) -> 357
A45: 阜阳 | B45: 42 | C45: 10 | D45: 20 | E45: 23 | F45: 7 | N45: =SUM(B45:M45) -> 102
A46: 贵阳 | B46: 44 | C46: 20 | D46: 16 | E46: 36 | F46: 33 | N46: =SUM(B46:M46) -> 149
A47: 昆明 | B47: 13 | C47: 21 | D47: 22 | E47: 14 | F47: 39 | N47: =SUM(B47:M47) -> 109
A48: 连江 | B48: 80 | C48: 63 | D48: 60 | E48: 61 | F48: 77 | N48: =SUM(B48:M48) -> 341
A49: 罗源 | B49: 79 | C49: 54 | D49: 92 | E49: 93 | F49: 56 | N49: =SUM(B49:M49) -> 374
A50: 闽江 | B50: 13 | C50: 12 | D50: 11 | E50: 13 | F50: 7 | N50: =SUM(B50:M50) -> 56
A51: 宁波 | B51: 86 | C51: 50 | D51: 83 | E51: 107 | F51: 77 | N51: =SUM(B51:M51) -> 403
A52: 腾冲 | B52: 3 | C52: 6 | D52: 5 | E52: 58 | F52: 15 | N52: =SUM(B52:M52) -> 87
A53: 长沙 | B53: 89 | C53: 28 | D53: 33 | E53: 56 | F53: 52 | N53: =SUM(B53:M53) -> 258
A54: 总计 | B54: =SUM(B41:B53) -> 683 | C54: =SUM(C41:C53) -> 492 | D54: =SUM(D41:D53) -> 546 | E54: =SUM(E41:E53) -> 643 | F54: =SUM(F41:F53) -> 539 | G54: =SUM(G41:G53) -> 0 | H54: =SUM(H41:H53) -> 0 | I54: =SUM(I41:I53) -> 0 | ... N54: =SUM(N41:N53) -> 2903
A57: 2026投诉回访满意工单
A58: 公司 | B58: 1月 | C58: 2月 | D58: 3月 | E58: 4月 | F58: 5月 | G58: 6月 | H58: 7月 | I58: 8月 | J58: 9月 | K58: 10月 | L58: 11月 | M58: 12月 | N58: 总计
A59: 版纳 | B59: 24 | C59: 28 | D59: 30 | E59: 19 | F59: 28 | N59: =SUM(B59:M59) -> 129
A60: 北城 | B60: 76 | C60: 32 | D60: 30 | E60: 48 | F60: 48 | N60: =SUM(B60:M60) -> 234
A61: 北京 | B61: 64 | C61: 43 | D61: 26 | E61: 50 | F61: 26 | N61: =SUM(B61:M61) -> 209
A62: 滨湖 | B62: 47 | C62: 37 | D62: 54 | E62: 38 | F62: 60 | N62: =SUM(B62:M62) -> 236
A63: 阜阳 | B63: 22 | C63: 3 | D63: 6 | E63: 12 | F63: 12 | N63: =SUM(B63:M63) -> 55
A64: 贵阳 | B64: 85 | C64: 30 | D64: 71 | E64: 69 | F64: 77 | N64: =SUM(B64:M64) -> 332
A65: 昆明 | B65: 63 | C65: 29 | D65: 61 | E65: 50 | F65: 63 | N65: =SUM(B65:M65) -> 266
A66: 连江 | B66: 78 | C66: 32 | D66: 34 | E66: 60 | F66: 57 | N66: =SUM(B66:M66) -> 261
A67: 罗源 | B67: 33 | C67: 13 | D67: 20 | E67: 19 | F67: 26 | N67: =SUM(B67:M67) -> 111
A68: 闽江 | B68: 19 | C68: 12 | D68: 23 | E68: 11 | F68: 5 | N68: =SUM(B68:M68) -> 70
A69: 宁波 | B69: 117 | C69: 41 | D69: 57 | E69: 87 | F69: 88 | N69: =SUM(B69:M69) -> 390
A70: 腾冲 | B70: 13 | C70: 4 | D70: 3 | E70: 8 | F70: 10 | N70: =SUM(B70:M70) -> 38
A71: 长沙 | B71: 53 | C71: 35 | D71: 31 | E71: 35 | F71: 43 | N71: =SUM(B71:M71) -> 197
A72: 总计 | B72: =SUM(B59:B71) -> 694 | C72: =SUM(C59:C71) -> 339 | D72: =SUM(D59:D71) -> 446 | E72: =SUM(E59:E71) -> 506 | F72: =SUM(F59:F71) -> 543 | G72: =SUM(G59:G71) -> 0 | H72: =SUM(H59:H71) -> 0 | I72: =SUM(I59:I71) -> 0 | ... N72: =SUM(N59:N71) -> 2528
A76: 2026投诉回访接通总量
A77: 公司 | B77: 1月 | C77: 2月 | D77: 3月 | E77: 4月 | F77: 5月 | G77: 6月 | H77: 7月 | I77: 8月 | J77: 9月 | K77: 10月 | L77: 11月 | M77: 12月 | N77: 总计
A78: 版纳 | B78: 81 | C78: 83 | D78: 62 | E78: 41 | F78: 52 | N78: =SUM(B78:M78) -> 319
A79: 北城 | B79: 125 | C79: 96 | D79: 78 | E79: 113 | F79: 118 | N79: =SUM(B79:M79) -> 530
A80: 北京 | B80: 115 | C80: 76 | D80: 67 | E80: 78 | F80: 54 | N80: =SUM(B80:M80) -> 390
A81: 滨湖 | B81: 124 | C81: 113 | D81: 137 | E81: 105 | F81: 114 | N81: =SUM(B81:M81) -> 593
A82: 阜阳 | B82: 64 | C82: 13 | D82: 26 | E82: 35 | F82: 19 | N82: =SUM(B82:M82) -> 157
A83: 贵阳 | B83: 129 | C83: 50 | D83: 87 | E83: 105 | F83: 110 | N83: =SUM(B83:M83) -> 481
A84: 昆明 | B84: 76 | C84: 50 | D84: 83 | E84: 64 | F84: 102 | N84: =SUM(B84:M84) -> 375
A85: 连江 | B85: 158 | C85: 95 | D85: 94 | E85: 121 | F85: 134 | N85: =SUM(B85:M85) -> 602
A86: 罗源 | B86: 112 | C86: 67 | D86: 112 | E86: 112 | F86: 82 | N86: =SUM(B86:M86) -> 485
A87: 闽江 | B87: 32 | C87: 24 | D87: 34 | E87: 24 | F87: 12 | N87: =SUM(B87:M87) -> 126
A88: 宁波 | B88: 203 | C88: 91 | D88: 140 | E88: 194 | F88: 165 | N88: =SUM(B88:M88) -> 793
A89: 腾冲 | B89: 16 | C89: 10 | D89: 8 | E89: 66 | F89: 25 | N89: =SUM(B89:M89) -> 125
A90: 长沙 | B90: 142 | C90: 63 | D90: 64 | E90: 91 | F90: 95 | N90: =SUM(B90:M90) -> 455
A91: 总计 | B91: =SUM(B78:B90) -> 1377 | C91: =SUM(C78:C90) -> 831 | D91: =SUM(D78:D90) -> 992 | E91: =SUM(E78:E90) -> 1149 | F91: =SUM(F78:F90) -> 1082 | G91: =SUM(G78:G90) -> 0 | H91: =SUM(H78:H90) -> 0 | I91: =SUM(I78:I90) -> 0 | ... N91: =SUM(N78:N90) -> 5431
B92: =B54+B72-B91 -> 0 | C92: =C54+C72-C91 -> 0 | D92: =D54+D72-D91 -> 0 | E92: =E54+E72-E91 -> 0 | F92: =F54+F72-F91 -> 0 | G92: =G54+G72-G91 -> 0 | H92: =H54+H72-H91 -> 0 | I92: =I54+I72-I91 -> 0 | ... N92: =N54+N72-N91 -> 0
A94: 2026未按时办结投诉
A95: 公司 | B95: 1月 | C95: 2月 | D95: 3月 | E95: 4月 | F95: 5月 | G95: 6月 | H95: 7月 | I95: 8月 | J95: 9月 | K95: 10月 | L95: 11月 | M95: 12月 | N95: 总计
A96: 版纳 | B96: 30 | C96: 8 | D96: 0 | E96: 4 | F96: 15 | N96: =SUM(B96:M96) -> 57
A97: 北城 | B97: 2 | C97: 0 | D97: 0 | E97: 2 | F97: 0 | N97: =SUM(B97:M97) -> 4
A98: 北京 | B98: 25 | C98: 9 | D98: 69 | E98: 24 | F98: 47 | N98: =SUM(B98:M98) -> 174
A99: 滨湖 | B99: 0 | C99: 1 | D99: 0 | E99: 2 | F99: 0 | N99: =SUM(B99:M99) -> 3
A100: 阜阳 | B100: 0 | C100: 0 | D100: 0 | E100: 0 | F100: 0 | N100: =SUM(B100:M100) -> 0
A101: 贵阳 | B101: 0 | C101: 0 | D101: 2 | E101: 1 | F101: 0 | N101: =SUM(B101:M101) -> 3
A102: 昆明 | B102: 53 | C102: 5 | D102: 0 | E102: 1 | F102: 2 | N102: =SUM(B102:M102) -> 61
A103: 连江 | B103: 0 | C103: 1 | D103: 0 | E103: 0 | F103: 0 | N103: =SUM(B103:M103) -> 1
A104: 罗源 | B104: 10 | C104: 7 | D104: 10 | E104: 30 | F104: 11 | N104: =SUM(B104:M104) -> 68
A105: 闽江 | B105: 2 | C105: 0 | D105: 0 | E105: 0 | F105: 0 | N105: =SUM(B105:M105) -> 2
A106: 宁波 | B106: 17 | C106: 23 | D106: 9 | E106: 21 | F106: 5 | N106: =SUM(B106:M106) -> 75
A107: 腾冲 | B107: 0 | C107: 1 | D107: 1 | E107: 0 | F107: 1 | N107: =SUM(B107:M107) -> 3
A108: 长沙 | B108: 3 | C108: 3 | D108: 0 | E108: 1 | F108: 1 | N108: =SUM(B108:M108) -> 8
A109: 总计 | B109: =SUM(B96:B108) -> 142 | C109: =SUM(C96:C108) -> 58 | D109: =SUM(D96:D108) -> 91 | E109: =SUM(E96:E108) -> 86 | F109: =SUM(F96:F108) -> 82 | G109: =SUM(G96:G108) -> 0 | H109: =SUM(H96:H108) -> 0 | I109: =SUM(I96:I108) -> 0 | ... N109: =SUM(N96:N108) -> 459
A113: 2026投诉满意度
A114: 公司 | B114: 1月 | C114: 2月 | D114: 3月 | E114: 4月 | F114: 5月 | G114: 6月 | H114: 7月 | I114: 8月 | J114: 9月 | K114: 10月 | L114: 11月 | M114: 12月 | N114: 总计
...

Sheet 设备设施管理
B2: 公司 | C2: 巡检完成率 | D2: 维保完成率 | E2: 现场巡查系数 | G2: 公司 | H2: 得分 | I2: 权重得分
B3: 版纳 | G3: 版纳 | H3: =(100*C3*50%+100*D3*50%)*E3 -> 0 | I3: =H3*0.1 -> 0
B4: 北城 | G4: 北城 | H4: =(100*C4*50%+100*D4*50%)*E4 -> 0 | I4: =H4*0.1 -> 0
B5: 北京 | G5: 北京 | H5: =(100*C5*50%+100*D5*50%)*E5 -> 0 | I5: =H5*0.1 -> 0
B6: 滨湖 | G6: 滨湖 | H6: =(100*C6*50%+100*D6*50%)*E6 -> 0 | I6: =H6*0.1 -> 0
B7: 阜阳 | G7: 阜阳 | H7: =(100*C7*50%+100*D7*50%)*E7 -> 0 | I7: =H7*0.1 -> 0
B8: 贵阳 | G8: 贵阳 | H8: =(100*C8*50%+100*D8*50%)*E8 -> 0 | I8: =H8*0.1 -> 0
B9: 昆明 | G9: 昆明 | H9: =(100*C9*50%+100*D9*50%)*E9 -> 0 | I9: =H9*0.1 -> 0
B10: 连江 | G10: 连江 | H10: =(100*C10*50%+100*D10*50%)*E10 -> 0 | I10: =H10*0.1 -> 0
B11: 罗源 | G11: 罗源 | H11: =(100*C11*50%+100*D11*50%)*E11 -> 0 | I11: =H11*0.1 -> 0
B12: 闽江 | G12: 闽江 | H12: =(100*C12*50%+100*D12*50%)*E12 -> 0 | I12: =H12*0.1 -> 0
B13: 宁波 | G13: 宁波 | H13: =(100*C13*50%+100*D13*50%)*E13 -> 0 | I13: =H13*0.1 -> 0
B14: 腾冲 | G14: 腾冲 | H14: =(100*C14*50%+100*D14*50%)*E14 -> 0 | I14: =H14*0.1 -> 0
... B16: 集团 | G16: 集团 | H16: =(100*C16*50%+100*D16*50%)*E16 -> 0 | I16: =H16*0.1 -> 0

Sheet 自用能耗成本
B2: 公司 | C2: 合计收入 | D2: 合计成本 | E2: 盈亏率 | F2: 24盈亏率 | G2: 同比差异 | H2: 修正情况 | J2: 公司 | K2: 得分 | L2: 权重得分
B3: 版纳 | J3: 版纳 | K3: 120 | L3: =K3*0.05 -> 6
B4: 北城 | J4: 北城 | K4: 113.49797 | L4: =K4*0.05 -> 5.6748985
B5: 北京 | J5: 北京 | K5: 119.04002 | L5: =K5*0.05 -> 5.9520011
B6: 滨湖 | J6: 滨湖 | K6: 120 | L6: =K6*0.05 -> 6
B7: 阜阳 | J7: 阜阳 | K7: 120 | L7: =K7*0.05 -> 6
B8: 贵阳 | J8: 贵阳 | K8: 111.35705 | L8: =K8*0.05 -> 5.5678524
B9: 昆明 | J9: 昆明 | K9: 79.413851 | L9: =K9*0.05 -> 3.9706925
B10: 连江 | J10: 连江 | K10: 120 | L10: =K10*0.05 -> 6
B11: 罗源 | J11: 罗源 | K11: 99.557215 | L11: =K11*0.05 -> 4.9778608
B12: 闽江 | J12: 闽江 | K12: 120 | L12: =K12*0.05 -> 6
B13: 宁波 | J13: 宁波 | K13: 115.43206 | L13: =K13*0.05 -> 5.7716028
B14: 腾冲 | J14: 腾冲 | K14: 75.824727 | L14: =K14*0.05 -> 3.7912363
... B16: 集团 | J16: 集团 | K16: 112.55535 | L16: =K16*0.05 -> 5.6277676

Sheet 基础信息抽查
A1: 2026年基础信息准确率
A2: 公司 | B2: 1月 | C2: 2月 | D2: 3月 | E2: 4月 | F2: 5月 | G2: 6月 | H2: 7月 | I2: 8月 | J2: 9月 | K2: 10月 | L2: 11月 | M2: 12月 | N2: 年度均值 | O2: 公司 | P2: 均值 | Q2: 得分 | R2: 权重得分
A3: 版纳 | B3: 0.90334572 | D3: 0.90688259 | E3: 0.88888889 | F3: 0.91290323 | N3: =AVERAGE(B3:M3) -> 0.90300511 | O3: 版纳 | P3: =AVERAGE(B3:M3) -> 0.90300511 | Q3: =ROUND(IF(P3>=95%,100,IF(P3>=75%,100-(95%-P3)/1%*3,40)),1) -> 85.9 | R3: =Q3*0.05 -> 4.295 | S3: 0.90334572 | T3: 0.44032922
A4: 北城 | B4: 0.9 | D4: 0.94112061 | E4: 0.99698492 | F4: 0.89963168 | N4: =AVERAGE(B4:M4) -> 0.9344343 | O4: 北城 | P4: =AVERAGE(B4:M4) -> 0.9344343 | Q4: =ROUND(IF(P4>=95%,100,IF(P4>=75%,100-(95%-P4)/1%*3,40)),1) -> 95.3 | R4: =Q4*0.05 -> 4.765 | S4: 0.9 | T4: 0.4620462
A5: 北京 | B5: 0.92519685 | D5: 0.92635659 | E5: 0.92241379 | F5: 0.9628866 | N5: =AVERAGE(B5:M5) -> 0.93421346 | O5: 北京 | P5: =AVERAGE(B5:M5) -> 0.93421346 | Q5: =ROUND(IF(P5>=95%,100,IF(P5>=75%,100-(95%-P5)/1%*3,40)),1) -> 95.3 | R5: =Q5*0.05 -> 4.765 | S5: 0.92519685 | T5: 0.61702128
A6: 滨湖 | B6: 0.82679739 | D6: 0.84090909 | E6: 0.85667216 | F6: 0.86911765 | N6: =AVERAGE(B6:M6) -> 0.84837407 | O6: 滨湖 | P6: =AVERAGE(B6:M6) -> 0.84837407 | Q6: =ROUND(IF(P6>=95%,100,IF(P6>=75%,100-(95%-P6)/1%*3,40)),1) -> 69.5 | R6: =Q6*0.05 -> 3.475 | S6: 0.82679739 | T6: 0.46640316
A7: 阜阳 | B7: 0.92546584 | D7: 0.93567251 | E7: 0.95302013 | F7: 0.93220339 | N7: =AVERAGE(B7:M7) -> 0.93659047 | O7: 阜阳 | P7: =AVERAGE(B7:M7) -> 0.93659047 | Q7: =ROUND(IF(P7>=95%,100,IF(P7>=75%,100-(95%-P7)/1%*3,40)),1) -> 96 | R7: =Q7*0.05 -> 4.8 | S7: 0.92546584 | T7: 0.55033557
A8: 贵阳 | B8: 0.9441402 | D8: 0.94376278 | E8: 0.94234801 | F8: 0.96737213 | N8: =AVERAGE(B8:M8) -> 0.94940578 | O8: 贵阳 | P8: 0.996 | Q8: =ROUND(IF(P8>=95%,100,IF(P8>=75%,100-(95%-P8)/1%*3,40)),1) -> 100 | R8: =Q8*0.05 -> 5 | S8: 0.9441402 | T8: 0.47911833
A9: 昆明 | B9: 0.98295455 | D9: 0.96056338 | E9: 0.93489583 | F9: 0.97132616 | N9: =AVERAGE(B9:M9) -> 0.96243498 | O9: 昆明 | P9: =AVERAGE(B9:M9) -> 0.96243498 | Q9: =ROUND(IF(P9>=95%,100,IF(P9>=75%,100-(95%-P9)/1%*3,40)),1) -> 100 | R9: =Q9*0.05 -> 5 | S9: 0.98295455 | T9: 0.56647399
A10: 连江 | B10: 0.92597765 | D10: 0.90769231 | E10: 0.94730392 | F10: 0.95733611 | N10: =AVERAGE(B10:M10) -> 0.9345775 | O10: 连江 | P10: =AVERAGE(B10:M10) -> 0.9345775 | Q10: =ROUND(IF(P10>=95%,100,IF(P10>=75%,100-(95%-P10)/1%*3,40)),1) -> 95.4 | R10: =Q10*0.05 -> 4.77 | S10: 0.92597765 | T10: 0.5158371
A11: 罗源 | B11: 0.95839753 | D11: 0.94714882 | E11: 0.95492958 | F11: 0.95454545 | N11: =AVERAGE(B11:M11) -> 0.95375535 | O11: 罗源 | P11: =AVERAGE(B11:M11) -> 0.95375535 | Q11: =ROUND(IF(P11>=95%,100,IF(P11>=75%,100-(95%-P11)/1%*3,40)),1) -> 100 | R11: =Q11*0.05 -> 5 | S11: 0.95839753 | T11: 0.52572347
A12: 闽江 | B12: 0.9375 | D12: 0.93886463 | E12: 0.89166667 | F12: 0.94921875 | N12: =AVERAGE(B12:M12) -> 0.92931251 | O12: 闽江 | P12: =AVERAGE(B12:M12) -> 0.92931251 | Q12: =ROUND(IF(P12>=95%,100,IF(P12>=75%,100-(95%-P12)/1%*3,40)),1) -> 93.8 | R12: =Q12*0.05 -> 4.69 | S12: 0.9375 | T12: 0.53333333
A13: 宁波 | B13: 0.89051095 | D13: 0.88846154 | E13: 0.88619403 | F13: 0.91917973 | N13: =AVERAGE(B13:M13) -> 0.89608656 | O13: 宁波 | P13: 0.936 | Q13: =ROUND(IF(P13>=95%,100,IF(P13>=75%,100-(95%-P13)/1%*3,40)),1) -> 95.8 | R13: =Q13*0.05 -> 4.79 | S13: 0.89051095 | T13: 0.46106557
A14: 腾冲 | B14: 0.88275862 | D14: 0.91056911 | E14: 0.85714286 | F14: 0.91017964 | N14: =AVERAGE(B14:M14) -> 0.89016256 | O14: 腾冲 | P14: =AVERAGE(B14:M14) -> 0.89016256 | Q14: =ROUND(IF(P14>=95%,100,IF(P14>=75%,100-(95%-P14)/1%*3,40)),1) -> 82 | R14: =Q14*0.05 -> 4.1 | S14: 0.88275862 | T14: 0.625
A15: 长沙 | B15: 0.92273731 | D15: 0.90361446 | E15: 0.91275168 | F15: 0.92110092 | N15: =AVERAGE(B15:M15) -> 0.91505109 | O15: 长沙 | P15: =AVERAGE(B15:M15) -> 0.91505109 | Q15: =ROUND(IF(P15>=95%,100,IF(P15>=75%,100-(95%-P15)/1%*3,40)),1) -> 89.5 | R15: =Q15*0.05 -> 4.475 | S15: 0.92273731 | T15: 0.50717703
A16: 总计 | B16: 0.9164288 | D16: 0.92045632 | E16: 0.93143034 | F16: 0.93440563 | N16: =AVERAGE(B16:M16) -> 0.92568027 | P16: =AVERAGE(B16:M16) -> 0.92568027 | S16: 0.9164288 | T16: 0.5012978
A20: 2025年基础信息准确率
A21: 公司 | B21: 1月 | C21: 2月 | D21: 3月 | E21: 4月 | F21: 5月 | G21: 6月 | H21: 7月 | I21: 8月 | J21: 9月 | K21: 10月 | L21: 11月 | M21: 12月 | N21: 年度均值
A22: 版纳 | B22: 0.88104089 | C22: 0.89361702 | D22: 0.90545455 | E22: 0.89315068 | F22: 0.90748031 | G22: 0.89618644 | H22: 0.93287037 | I22: 0.92814371 | J22: 0.94230769 | L22: 0.96747967 | M22: 0 | N22: =AVERAGE(B22:M22) -> 0.83161194
A23: 北城 | B23: 0.96035242 | C23: 0.95909423 | D23: 0.93871665 | E23: 0.95 | F23: 0.9486458 | G23: 0.94676442 | H23: 0.96996047 | I23: 0.94805803 | J23: 0.95989613 | L23: 0.95813205 | M23: 0.81925926 | N23: =AVERAGE(B23:M23) -> 0.94171632
A24: 北京 | B24: 0.97597598 | C24: 0.95211268 | D24: 0.94647887 | E24: 0.94959677 | F24: 0.94751381 | G24: 0.94928479 | H24: 0.96194503 | I24: 0.96049046 | J24: 0.95229983 | L24: 0.97887324 | M24: 0.93396226 | N24: =AVERAGE(B24:M24) -> 0.95532125
A25: 滨湖 | B25: 0.942324 | C25: 0.94463087 | D25: 0.93333333 | E25: 0.93100276 | F25: 0.93813776 | G25: 0.93084371 | H25: 0.93044129 | I25: 0.92495637 | J25: 0.92639734 | L25: 0.96327684 | M25: 1 | N25: =AVERAGE(B25:M25) -> 0.94230402
A26: 阜阳 | B26: 0.95789474 | C26: 0.97008547 | D26: 0.96787149 | E26: 0.95081967 | F26: 0.91743119 | G26: 0.9742268 | H26: 0.96439169 | I26: 0.96497373 | J26: 0.95913978 | L26: 0.9921875 | M26: 1 | N26: =AVERAGE(B26:M26) -> 0.96536564
A27: 贵阳 | B27: 0.9592721 | C27: 0.97024346 | D27: 0.95604396 | E27: 0.96643878 | F27: 0.97345133 | G27: 0.94391678 | H27: 0.97776655 | I27: 0.97580398 | J27: 0.96951702 | L27: 0.9305073 | M27: 1 | N27: =AVERAGE(B27:M27) -> 0.96572375
A28: 昆明 | B28: 0.97727273 | C28: 0.9751693 | D28: 0.95842956 | E28: 0.92628205 | F28: 0.9516129 | G28: 0.96246973 | H28: 0.96944444 | I28: 0.96655518 | J28: 0.96283391 | L28: 0.95625 | M28: 0.91666667 | N28: =AVERAGE(B28:M28) -> 0.95663514
A29: 连江 | B29: 0.96491228 | C29: 0.9608802 | D29: 0.95298602 | E29: 0.95837024 | F29: 0.96213658 | G29: 0.93873762 | H29: 0.95676047 | I29: 0.93124006 | J29: 0.93753123 | L29: 0.97876106 | M29: 1 | N29: =AVERAGE(B29:M29) -> 0.95839234
A30: 罗源 | B30: 0.97081413 | C30: 0.96396396 | D30: 0.95820433 | E30: 0.95762712 | F30: 0.95231214 | G30: 0.95010115 | H30: 0.97229219 | I30: 0.95508391 | J30: 0.95087065 | L30: 0.93908629 | M30: 1 | N30: =AVERAGE(B30:M30) -> 0.96094144
A31: 闽江 | B31: 0.95112782 | C31: 0.97026022 | D31: 0.95564516 | E31: 0.92196532 | F31: 0.93139293 | G31: 0.93904762 | H31: 0.96856582 | I31: 0.94146341 | J31: 0.95290424 | L31: 0.86842105 | M31: 1 | N31: =AVERAGE(B31:M31) -> 0.94552669
A32: 宁波 | B32: 0.93222222 | C32: 0.93691589 | D32: 0.93502538 | E32: 0.92548435 | F32: 0.925 | G32: 0.94618145 | H32: 0.93883792 | I32: 0.9310183 | J32: 0.93381906 | L32: 0.9487909 | M32: 0.85495119 | N32: =AVERAGE(B32:M32) -> 0.92802242
A33: 腾冲 | B33: 0.97765363 | C33: 0.94193548 | D33: 0.9378882 | E33: 0.94418605 | F33: 0.9269103 | G33: 0.9252669 | H33: 0.94186047 | I33: 0.91706161 | J33: 0.92774566 | L33: 0.975 | M33: 0.75 | N33: =AVERAGE(B33:M33) -> 0.92413712
... A35: 总计 | B35: 0.9552257 | C35: 0.95463868 | D35: 0.94557736 | E35: 0.94379289 | F35: 0.94615385 | G35: 0.94451629 | H35: 0.96062875 | I35: 0.94780074 | J35: 0.94969615 | L35: 0.95210424 | M35: 0.8474359 | N35: =AVERAGE(B35:M35) -> 0.94068823

Sheet 400知晓率
A1: 2025年知晓400电话比例
A2: 公司 | B2: 1月 | C2: 2月 | D2: 3月 | E2: 4月 | F2: 5月 | G2: 6月 | H2: 7月 | I2: 8月 | J2: 9月 | K2: 10月 | L2: 11月 | M2: 12月 | N2: 年度均值 | P2: 公司 | Q2: 均值 | R2: 得分 | S2: 权重得分
A3: 版纳 | B3: 0.44032922 | D3: 0.45982143 | E3: 0.50925926 | F3: 0.61130742 | N3: =AVERAGE(B3:M3) -> 0.50517933 | P3: 版纳 | Q3: =AVERAGE(B3:M3) -> 0.50517933 | R3: =ROUND(IF(Q3=50%,100,IF(Q3>50%,100+(Q3-50%)/1%*2,100-(50%-Q3)/1%*2)),1) -> 101 | S3: =R3*0.05 -> 5.05
A4: 北城 | B4: 0.4620462 | D4: 0.46014127 | E4: 0.46673387 | F4: 0.4370522 | N4: =AVERAGE(B4:M4) -> 0.45649339 | P4: 北城 | Q4: 0.5054 | R4: =ROUND(IF(Q4=50%,100,IF(Q4>50%,100+(Q4-50%)/1%*2,100-(50%-Q4)/1%*2)),1) -> 101.1 | S4: =R4*0.05 -> 5.055
A5: 北京 | B5: 0.61702128 | D5: 0.65271967 | E5: 0.69626168 | F5: 0.86723769 | N5: =AVERAGE(B5:M5) -> 0.70831008 | P5: 北京 | Q5: =AVERAGE(B5:M5) -> 0.70831008 | R5: =ROUND(IF(Q5=50%,100,IF(Q5>50%,100+(Q5-50%)/1%*2,100-(50%-Q5)/1%*2)),1) -> 141.7 | S5: =R5*0.05 -> 7.085
A6: 滨湖 | B6: 0.46640316 | D6: 0.41119691 | E6: 0.45961538 | F6: 0.51945854 | N6: =AVERAGE(B6:M6) -> 0.4641685 | P6: 滨湖 | Q6: =AVERAGE(B6:M6) -> 0.4641685 | R6: =ROUND(IF(Q6=50%,100,IF(Q6>50%,100+(Q6-50%)/1%*2,100-(50%-Q6)/1%*2)),1) -> 92.8 | S6: =R6*0.05 -> 4.64
A7: 阜阳 | B7: 0.55033557 | D7: 0.49375 | E7: 0.58450704 | F7: 0.61818182 | N7: =AVERAGE(B7:M7) -> 0.56169361 | P7: 阜阳 | Q7: =AVERAGE(B7:M7) -> 0.56169361 | R7: =ROUND(IF(Q7=50%,100,IF(Q7>50%,100+(Q7-50%)/1%*2,100-(50%-Q7)/1%*2)),1) -> 112.3 | S7: =R7*0.05 -> 5.615
A8: 贵阳 | B8: 0.47911833 | D8: 0.49512459 | E8: 0.58731924 | F8: 0.57976299 | N8: =AVERAGE(B8:M8) -> 0.53533129 | P8: 贵阳 | Q8: 0.523 | R8: =ROUND(IF(Q8=50%,100,IF(Q8>50%,100+(Q8-50%)/1%*2,100-(50%-Q8)/1%*2)),1) -> 104.6 | S8: =R8*0.05 -> 5.23
A9: 昆明 | B9: 0.56647399 | D9: 0.50439883 | E9: 0.51532033 | F9: 0.68819188 | N9: =AVERAGE(B9:M9) -> 0.56859626 | P9: 昆明 | Q9: =AVERAGE(B9:M9) -> 0.56859626 | R9: =ROUND(IF(Q9=50%,100,IF(Q9>50%,100+(Q9-50%)/1%*2,100-(50%-Q9)/1%*2)),1) -> 113.7 | S9: =R9*0.05 -> 5.685
A10: 连江 | B10: 0.5158371 | D10: 0.52080123 | E10: 0.65847348 | F10: 0.69673913 | N10: =AVERAGE(B10:M10) -> 0.59796274 | P10: 连江 | Q10: =AVERAGE(B10:M10) -> 0.59796274 | R10: =ROUND(IF(Q10=50%,100,IF(Q10>50%,100+(Q10-50%)/1%*2,100-(50%-Q10)/1%*2)),1) -> 119.6 | S10: =R10*0.05 -> 5.98
A11: 罗源 | B11: 0.52572347 | D11: 0.55359765 | E11: 0.58849558 | F11: 0.56190476 | N11: =AVERAGE(B11:M11) -> 0.55743037 | P11: 罗源 | Q11: =AVERAGE(B11:M11) -> 0.55743037 | R11: =ROUND(IF(Q11=50%,100,IF(Q11>50%,100+(Q11-50%)/1%*2,100-(50%-Q11)/1%*2)),1) -> 111.5 | S11: =R11*0.05 -> 5.575
A12: 闽江 | B12: 0.53333333 | D12: 0.56744186 | E12: 0.52336449 | F12: 0.5473251 | N12: =AVERAGE(B12:M12) -> 0.5428662 | P12: 闽江 | Q12: =AVERAGE(B12:M12) -> 0.5428662 | R12: =ROUND(IF(Q12=50%,100,IF(Q12>50%,100+(Q12-50%)/1%*2,100-(50%-Q12)/1%*2)),1) -> 108.6 | S12: =R12*0.05 -> 5.43
A13: 宁波 | B13: 0.46106557 | D13: 0.46536797 | E13: 0.48842105 | F13: 0.69422572 | N13: =AVERAGE(B13:M13) -> 0.52727008 | P13: 宁波 | Q13: 0.459 | R13: =ROUND(IF(Q13=50%,100,IF(Q13>50%,100+(Q13-50%)/1%*2,100-(50%-Q13)/1%*2)),1) -> 91.8 | S13: =R13*0.05 -> 4.59
A14: 腾冲 | B14: 0.625 | D14: 0.45535714 | E14: 0.50877193 | F14: 0.66447368 | N14: =AVERAGE(B14:M14) -> 0.56340069 | P14: 腾冲 | Q14: =AVERAGE(B14:M14) -> 0.56340069 | R14: =ROUND(IF(Q14=50%,100,IF(Q14>50%,100+(Q14-50%)/1%*2,100-(50%-Q14)/1%*2)),1) -> 112.7 | S14: =R14*0.05 -> 5.635
A15: 长沙 | B15: 0.50717703 | D15: 0.41066667 | E15: 0.50980392 | F15: 0.57569721 | N15: =AVERAGE(B15:M15) -> 0.50083621 | P15: 长沙 | Q15: =AVERAGE(B15:M15) -> 0.50083621 | R15: =ROUND(IF(Q15=50%,100,IF(Q15>50%,100+(Q15-50%)/1%*2,100-(50%-Q15)/1%*2)),1) -> 100.2 | S15: =R15*0.05 -> 5.01
A16: 总计 | B16: 0.5012978 | D16: 0.49117148 | E16: 0.54546969 | F16: 0.60906401 | N16: =AVERAGE(B16:M16) -> 0.53675074 | P16: 总计 | Q16: =AVERAGE(Q3:Q15) -> 0.54291107 | R16: =ROUND(IF(Q16=50%,100,IF(Q16>50%,100+(Q16-50%)/1%*2,100-(50%-Q16)/1%*2)),1) -> 108.6 | S16: =R16*0.05 -> 5.43
A21: 2025年知晓400电话比例
A22: 公司 | B22: 1月 | C22: 2月 | D22: 3月 | E22: 4月 | F22: 5月 | G22: 6月 | H22: 7月 | I22: 8月 | J22: 9月 | K22: 10月 | L22: 11月 | M22: 12月 | N22: 年度均值
A23: 版纳 | B23: 0.52320675 | C23: 0.47222222 | D23: 0.55421687 | E23: 0.49079755 | F23: 0.51409978 | G23: 0.52955083 | H23: 0.39205955 | I23: 0.35870968 | J23: 0.42687075 | L23: 0.7394958 | M23: 0 | N23: =AVERAGE(B23:M23) -> 0.45465725
A24: 北城 | B24: 0.47247706 | C24: 0.42269612 | D24: 0.40168971 | E24: 0.45077973 | F24: 0.45346681 | G24: 0.52558923 | H24: 0.41198044 | I24: 0.43213228 | J24: 0.4667869 | L24: 0.53613445 | M24: 0.1482821 | N24: =AVERAGE(B24:M24) -> 0.42927407
A25: 北京 | B25: 0.68615385 | C25: 0.64201183 | D25: 0.68452381 | E25: 0.67303609 | F25: 0.67055394 | G25: 0.63424658 | H25: 0.54505495 | I25: 0.53758865 | J25: 0.59033989 | L25: 0.73201439 | M25: 0.14141414 | N25: =AVERAGE(B25:M25) -> 0.5942671
A26: 滨湖 | B26: 0.47434743 | C26: 0.45559503 | D26: 0.55428571 | E26: 0.5 | F26: 0.52277362 | G26: 0.46805349 | H26: 0.43569132 | I26: 0.44292453 | J26: 0.45878136 | L26: 0.6568915 | M26: 0.66666667 | N26: =AVERAGE(B26:M26) -> 0.51236461
A27: 阜阳 | B27: 0.62087912 | C27: 0.57268722 | D27: 0.50622407 | E27: 0.49137931 | F27: 0.534 | G27: 0.58730159 | H27: 0.56923077 | I27: 0.53720508 | J27: 0.53811659 | L27: 0.4488189 | M27: 0 | N27: =AVERAGE(B27:M27) -> 0.49144024
A28: 贵阳 | B28: 0.46522132 | C28: 0.48884758 | D28: 0.4683908 | E28: 0.50803859 | F28: 0.485 | G28: 0.46190704 | H28: 0.46666667 | I28: 0.45543001 | J28: 0.498 | L28: 0.54742345 | M28: 0.53 | N28: =AVERAGE(B28:M28) -> 0.48862959
A29: 昆明 | B29: 0.52790698 | C29: 0.55555556 | D29: 0.56626506 | E29: 0.5432526 | F29: 0.57105606 | G29: 0.52830189 | H29: 0.52578797 | I29: 0.47318339 | J29: 0.52352232 | L29: 0.66013072 | M29: 0.3030303 | N29: =AVERAGE(B29:M29) -> 0.52527208
A30: 连江 | B30: 0.54805195 | C30: 0.54961832 | D30: 0.59066667 | E30: 0.55637708 | F30: 0.59522136 | G30: 0.5629532 | H30: 0.50789096 | I30: 0.48997012 | J30: 0.48187633 | L30: 0.74141049 | M30: 0.25 | N30: =AVERAGE(B30:M30) -> 0.53400332
A31: 罗源 | B31: 0.56329114 | C31: 0.59034268 | D31: 0.57996769 | E31: 0.51327434 | F31: 0.55007587 | G31: 0.51312988 | H31: 0.54835924 | I31: 0.5374677 | J31: 0.4911707 | L31: 0.75675676 | M31: 0.66666667 | N31: =AVERAGE(B31:M31) -> 0.57368206
A32: 闽江 | B32: 0.57312253 | C32: 0.58237548 | D32: 0.57383966 | E32: 0.49216301 | F32: 0.55133929 | G32: 0.49492901 | H32: 0.53752535 | I32: 0.51554404 | J32: 0.52059308 | L32: 0.74747475 | M32: 0.33333333 | N32: =AVERAGE(B32:M32) -> 0.53838541
A33: 宁波 | B33: 0.48271752 | C33: 0.48628429 | D33: 0.4907709 | E33: 0.39694042 | F33: 0.42076167 | G33: 0.51083424 | H33: 0.42996743 | I33: 0.43649194 | J33: 0.47269181 | L33: 0.64617691 | M33: 0.20065253 | N33: =AVERAGE(B33:M33) -> 0.45220815
A34: 腾冲 | B34: 0.52 | C34: 0.57534247 | D34: 0.40397351 | E34: 0.50738916 | F34: 0.54480287 | G34: 0.53076923 | H34: 0.5473251 | I34: 0.45219638 | J34: 0.52336449 | L34: 0.58974359 | M34: 0.66666667 | N34: =AVERAGE(B34:M34) -> 0.53287031
... A36: 总计 | B36: 0.51229143 | C36: 0.50612915 | D36: 0.51381588 | E36: 0.49723859 | F36: 0.51192412 | G36: 0.51721215 | H36: 0.46858598 | I36: 0.46277141 | J36: 0.47872971 | L36: 0.63473275 | M36: 0.18078669 | N36: =AVERAGE(B36:M36) -> 0.48038344

Sheet 重大事项扣罚
A1: 2024年重大事项扣罚情况（单项奖惩）
A2: 公司 | B2: 1月 | C2: 2月 | D2: 3月 | E2: 4月 | F2: 5月 | G2: 6月 | H2: 7月 | I2: 8月 | J2: 9月 | K2: 10月 | L2: 11月 | M2: 12月 | N2: 扣分合计 | P2: 公司 | Q2: 得分
A3: 版纳 | N3: =SUM(B3:M3) -> 0 | P3: 版纳 | Q3: =N3 -> 0
A4: 北城 | N4: =SUM(B4:M4) -> 0 | P4: 北城 | Q4: =N4 -> 0
A5: 北京 | N5: =SUM(B5:M5) -> 0 | P5: 北京 | Q5: =N5 -> 0
A6: 滨湖 | N6: =SUM(B6:M6) -> 0 | P6: 滨湖 | Q6: =N6 -> 0
A7: 阜阳 | N7: =SUM(B7:M7) -> 0 | P7: 阜阳 | Q7: =N7 -> 0
A8: 贵阳 | N8: =SUM(B8:M8) -> 0 | P8: 贵阳 | Q8: =N8 -> 0
A9: 昆明 | N9: =SUM(B9:M9) -> 0 | P9: 昆明 | Q9: =N9 -> 0
A10: 连江 | N10: =SUM(B10:M10) -> 0 | P10: 连江 | Q10: =N10 -> 0
A11: 罗源 | N11: =SUM(B11:M11) -> 0 | P11: 罗源 | Q11: =N11 -> 0
A12: 闽江 | N12: =SUM(B12:M12) -> 0 | P12: 闽江 | Q12: =N12 -> 0
A13: 宁波 | N13: =SUM(B13:M13) -> 0 | P13: 宁波 | Q13: =N13 -> 0
A14: 腾冲 | N14: =SUM(B14:M14) -> 0 | P14: 腾冲 | Q14: =N14 -> 0
A15: 长沙 | N15: =SUM(B15:M15) -> 0 | P15: 长沙 | Q15: =N15 -> 0

Sheet 单项奖惩
A1: 2025年单项奖惩统计台账
A2: 更新日期：2025年11月13日
A3: 序号 | B3: 公司 | C3: 日期 | D3: 奖惩类型 | E3: 奖惩事由 | F3: 奖励星级 | G3: 处罚星级 | H3: 奖惩金额/万元 | I3: KPI扣分 | J3: 文件名称 | K3: 备注
A4: 1
A5: 2
A6: 3
A7: 4
A8: 5
A9: 6
A10: 7
A11: 8
A12: 9
A13: 10
A14: 11
A15: 12
... A17: 14

Sheet 投诉评分
A1: 1月 | Q1: 2月
A2: 公司 | B2: 1分 | C2: 2分 | D2: 3分 | E2: 4分 | F2: 5分 | G2: 6分 | H2: 7分 | I2: 8分 | J2: 9分 | K2: 10分 | L2: 合计 | M2: 满意度 | Q2: 公司 | R2: 1分 | S2: 2分 | T2: 3分 | U2: 4分 | V2: 5分 | W2: 6分 | X2: 7分 | Y2: 8分 | Z2: 9分 | AA2: 10分 | AB2: 合计 | AC2: 满意度
A3: 版纳 | M3: =(B3*1+C3*2+D3*3+E3*4+F3*5+G3*6+H3*7+I3*8+J3*9+K3*10)/L3 -> #DIV/0! | Q3: 版纳 | R3: 32 | S3: 6 | T3: 2 | V3: 10 | W3: 2 | X3: 3 | Y3: 4 | Z3: 5 | AA3: 13 | AB3: 77 | AC3: =(R3*1+S3*2+T3*3+U3*4+V3*5+W3*6+X3*7+Y3*8+Z3*9+AA3*10)/AB3 -> 4.4155844
A4: 北城 | M4: =(B4*1+C4*2+D4*3+E4*4+F4*5+G4*6+H4*7+I4*8+J4*9+K4*10)/L4 -> #DIV/0! | Q4: 北城 | R4: 34 | T4: 4 | V4: 14 | W4: 11 | X4: 1 | Y4: 4 | AA4: 28 | AB4: 96 | AC4: =(R4*1+S4*2+T4*3+U4*4+V4*5+W4*6+X4*7+Y4*8+Z4*9+AA4*10)/AB4 -> 5.21875
A5: 北京 | M5: =(B5*1+C5*2+D5*3+E5*4+F5*5+G5*6+H5*7+I5*8+J5*9+K5*10)/L5 -> #DIV/0! | Q5: 北京 | R5: 27 | V5: 2 | X5: 4 | Y5: 9 | Z5: 2 | AA5: 31 | AB5: 75 | AC5: =(R5*1+S5*2+T5*3+U5*4+V5*5+W5*6+X5*7+Y5*8+Z5*9+AA5*10)/AB5 -> 6.2
A6: 滨湖 | M6: =(B6*1+C6*2+D6*3+E6*4+F6*5+G6*6+H6*7+I6*8+J6*9+K6*10)/L6 -> #DIV/0! | Q6: 滨湖 | R6: 48 | S6: 3 | T6: 2 | U6: 1 | V6: 8 | W6: 5 | X6: 9 | Y6: 5 | Z6: 3 | AA6: 29 | AB6: 113 | AC6: =(R6*1+S6*2+T6*3+U6*4+V6*5+W6*6+X6*7+Y6*8+Z6*9+AA6*10)/AB6 -> 4.9026549
A7: 阜阳 | M7: =(B7*1+C7*2+D7*3+E7*4+F7*5+G7*6+H7*7+I7*8+J7*9+K7*10)/L7 -> #DIV/0! | Q7: 阜阳 | R7: 9 | V7: 1 | Y7: 2 | AA7: 1 | AB7: 13 | AC7: =(R7*1+S7*2+T7*3+U7*4+V7*5+W7*6+X7*7+Y7*8+Z7*9+AA7*10)/AB7 -> 3.0769231
A8: 贵阳 | M8: =(B8*1+C8*2+D8*3+E8*4+F8*5+G8*6+H8*7+I8*8+J8*9+K8*10)/L8 -> #DIV/0! | Q8: 贵阳 | R8: 8 | V8: 5 | W8: 3 | X8: 4 | Y8: 4 | Z8: 4 | AA8: 22 | AB8: 50 | AC8: =(R8*1+S8*2+T8*3+U8*4+V8*5+W8*6+X8*7+Y8*8+Z8*9+AA8*10)/AB8 -> 7.34
A9: 昆明 | M9: =(B9*1+C9*2+D9*3+E9*4+F9*5+G9*6+H9*7+I9*8+J9*9+K9*10)/L9 -> #DIV/0! | Q9: 昆明 | R9: 14 | T9: 2 | V9: 2 | W9: 3 | Y9: 10 | Z9: 2 | AA9: 26 | AB9: 59 | AC9: =(R9*1+S9*2+T9*3+U9*4+V9*5+W9*6+X9*7+Y9*8+Z9*9+AA9*10)/AB9 -> 6.8813559
A10: 连江 | M10: =(B10*1+C10*2+D10*3+E10*4+F10*5+G10*6+H10*7+I10*8+J10*9+K10*10)/L10 -> #DIV/0! | Q10: 连江 | R10: 47 | U10: 2 | V10: 9 | W10: 1 | X10: 4 | Y10: 2 | Z10: 2 | AA10: 28 | AB10: 95 | AC10: =(R10*1+S10*2+T10*3+U10*4+V10*5+W10*6+X10*7+Y10*8+Z10*9+AA10*10)/AB10 -> 4.7157895
A11: 罗源 | M11: =(B11*1+C11*2+D11*3+E11*4+F11*5+G11*6+H11*7+I11*8+J11*9+K11*10)/L11 -> #DIV/0! | Q11: 罗源 | R11: 44 | S11: 1 | T11: 3 | V11: 3 | W11: 1 | X11: 2 | Y11: 4 | Z11: 1 | AA11: 8 | AB11: 67 | AC11: =(R11*1+S11*2+T11*3+U11*4+V11*5+W11*6+X11*7+Y11*8+Z11*9+AA11*10)/AB11 -> 3.1492537
A12: 闽江 | M12: =(B12*1+C12*2+D12*3+E12*4+F12*5+G12*6+H12*7+I12*8+J12*9+K12*10)/L12 -> #DIV/0! | Q12: 闽江 | R12: 9 | U12: 1 | V12: 1 | X12: 1 | Y12: 2 | Z12: 1 | AA12: 9 | AB12: 24 | AC12: =(R12*1+S12*2+T12*3+U12*4+V12*5+W12*6+X12*7+Y12*8+Z12*9+AA12*10)/AB12 -> 5.8333333
A13: 宁波 | M13: =(B13*1+C13*2+D13*3+E13*4+F13*5+G13*6+H13*7+I13*8+J13*9+K13*10)/L13 -> #DIV/0! | Q13: 宁波 | R13: 39 | S13: 3 | V13: 5 | X13: 3 | Y13: 3 | Z13: 6 | AA13: 32 | AB13: 91 | AC13: =(R13*1+S13*2+T13*3+U13*4+V13*5+W13*6+X13*7+Y13*8+Z13*9+AA13*10)/AB13 -> 5.3736264
A14: 腾冲 | M14: =(B14*1+C14*2+D14*3+E14*4+F14*5+G14*6+H14*7+I14*8+J14*9+K14*10)/L14 -> #DIV/0! | Q14: 腾冲 | V14: 3 | W14: 1 | X14: 2 | Y14: 2 | AA14: 2 | AB14: 10 | AC14: =(R14*1+S14*2+T14*3+U14*4+V14*5+W14*6+X14*7+Y14*8+Z14*9+AA14*10)/AB14 -> 7.1
A15: 长沙 | M15: =(B15*1+C15*2+D15*3+E15*4+F15*5+G15*6+H15*7+I15*8+J15*9+K15*10)/L15 -> #DIV/0! | Q15: 长沙 | R15: 18 | S15: 1 | T15: 1 | U15: 1 | V15: 3 | X15: 4 | Y15: 6 | Z15: 6 | AA15: 24 | AB15: 64 | AC15: =(R15*1+S15*2+T15*3+U15*4+V15*5+W15*6+X15*7+Y15*8+Z15*9+AA15*10)/AB15 -> 6.4375
A16: 总计 | M16: =(B16*1+C16*2+D16*3+E16*4+F16*5+G16*6+H16*7+I16*8+J16*9+K16*10)/L16 -> #DIV/0! | Q16: 总计 | R16: 329 | S16: 14 | T16: 14 | U16: 5 | V16: 66 | W16: 27 | X16: 37 | Y16: 57 | Z16: 32 | AA16: 253 | AB16: 834 | AC16: =(R16*1+S16*2+T16*3+U16*4+V16*5+W16*6+X16*7+Y16*8+Z16*9+AA16*10)/AB16 -> 5.3285372
A19: 3月 | Q19: 4月
A20: 公司 | B20: 1分 | C20: 2分 | D20: 3分 | E20: 4分 | F20: 5分 | G20: 6分 | H20: 7分 | I20: 8分 | J20: 9分 | K20: 10分 | L20: 合计 | M20: 满意度 | Q20: 公司 | R20: 1分 | S20: 2分 | T20: 3分 | U20: 4分 | V20: 5分 | W20: 6分 | X20: 7分 | Y20: 8分 | Z20: 9分 | AA20: 10分 | AB20: 合计 | AC20: 满意度
A21: 版纳 | B21: 26 | C21: 2 | D21: 1 | E21: 2 | F21: 6 | I21: 7 | J21: 4 | K21: 19 | L21: 67 | M21: =(B21*1+C21*2+D21*3+E21*4+F21*5+G21*6+H21*7+I21*8+J21*9+K21*10)/L21 -> 5.2686567 | Q21: 版纳 | R21: 13 | V21: 4 | W21: 3 | X21: 2 | Y21: 5 | Z21: 3 | AA21: 11 | AB21: 41 | AC21: =(R21*1+S21*2+T21*3+U21*4+V21*5+W21*6+X21*7+Y21*8+Z21*9+AA21*10)/AB21 -> 5.902439
A22: 北城 | B22: 34 | D22: 2 | F22: 8 | G22: 4 | I22: 4 | J22: 5 | K22: 21 | L22: 78 | M22: =(B22*1+C22*2+D22*3+E22*4+F22*5+G22*6+H22*7+I22*8+J22*9+K22*10)/L22 -> 5.0128205 | Q22: 北城 | R22: 51 | S22: 3 | T22: 1 | V22: 6 | W22: 1 | X22: 3 | Y22: 15 | Z22: 2 | AA22: 31 | AB22: 113 | AC22: =(R22*1+S22*2+T22*3+U22*4+V22*5+W22*6+X22*7+Y22*8+Z22*9+AA22*10)/AB22 -> 5
A23: 北京 | B23: 26 | C23: 1 | D23: 2 | F23: 6 | G23: 6 | H23: 1 | I23: 5 | J23: 2 | K23: 19 | L23: 68 | M23: =(B23*1+C23*2+D23*3+E23*4+F23*5+G23*6+H23*7+I23*8+J23*9+K23*10)/L23 -> 5.2205882 | Q23: 北京 | R23: 10 | T23: 17 | V23: 2 | W23: 1 | X23: 3 | Y23: 12 | Z23: 13 | AA23: 25 | AB23: 83 | AC23: =(R23*1+S23*2+T23*3+U23*4+V23*5+W23*6+X23*7+Y23*8+Z23*9+AA23*10)/AB23 -> 6.7590361
A24: 滨湖 | B24: 57 | D24: 2 | E24: 1 | F24: 11 | G24: 8 | H24: 4 | I24: 16 | J24: 9 | K24: 29 | L24: 137 | M24: =(B24*1+C24*2+D24*3+E24*4+F24*5+G24*6+H24*7+I24*8+J24*9+K24*10)/L24 -> 5.0875912 | Q24: 滨湖 | R24: 54 | T24: 1 | V24: 3 | W24: 6 | X24: 3 | Y24: 8 | Z24: 6 | AA24: 24 | AB24: 105 | AC24: =(R24*1+S24*2+T24*3+U24*4+V24*5+W24*6+X24*7+Y24*8+Z24*9+AA24*10)/AB24 -> 4.6380952
A25: 阜阳 | B25: 14 | F25: 5 | H25: 1 | J25: 3 | K25: 3 | L25: 26 | M25: =(B25*1+C25*2+D25*3+E25*4+F25*5+G25*6+H25*7+I25*8+J25*9+K25*10)/L25 -> 3.9615385 | Q25: 阜阳 | R25: 19 | V25: 4 | AA25: 12 | AB25: 35 | AC25: =(R25*1+S25*2+T25*3+U25*4+V25*5+W25*6+X25*7+Y25*8+Z25*9+AA25*10)/AB25 -> 4.5428571
A26: 贵阳 | B26: 11 | F26: 2 | G26: 1 | H26: 2 | I26: 11 | J26: 6 | K26: 54 | L26: 87 | M26: =(B26*1+C26*2+D26*3+E26*4+F26*5+G26*6+H26*7+I26*8+J26*9+K26*10)/L26 -> 8.3103448 | Q26: 贵阳 | R26: 23 | S26: 1 | T26: 3 | U26: 1 | V26: 4 | W26: 3 | X26: 3 | Y26: 13 | Z26: 11 | AA26: 45 | AB26: 107 | AC26: =(R26*1+S26*2+T26*3+U26*4+V26*5+W26*6+X26*7+Y26*8+Z26*9+AA26*10)/AB26 -> 7.0093458
A27: 昆明 | B27: 6 | C27: 2 | D27: 3 | E27: 1 | F27: 2 | G27: 3 | H27: 6 | I27: 8 | J27: 13 | K27: 40 | L27: 84 | M27: =(B27*1+C27*2+D27*3+E27*4+F27*5+G27*6+H27*7+I27*8+J27*9+K27*10)/L27 -> 8.0238095 | Q27: 昆明 | R27: 6 | W27: 7 | X27: 1 | Y27: 11 | Z27: 5 | AA27: 34 | AB27: 64 | AC27: =(R27*1+S27*2+T27*3+U27*4+V27*5+W27*6+X27*7+Y27*8+Z27*9+AA27*10)/AB27 -> 8.25
A28: 连江 | B28: 39 | D28: 4 | E28: 1 | F28: 6 | G28: 8 | H28: 2 | I28: 11 | J28: 2 | K28: 21 | L28: 94 | M28: =(B28*1+C28*2+D28*3+E28*4+F28*5+G28*6+H28*7+I28*8+J28*9+K28*10)/L28 -> 4.9255319 | Q28: 连江 | R28: 39 | S28: 6 | T28: 2 | V28: 6 | W28: 5 | X28: 3 | Y28: 11 | Z28: 7 | AA28: 42 | AB28: 121 | AC28: =(R28*1+S28*2+T28*3+U28*4+V28*5+W28*6+X28*7+Y28*8+Z28*9+AA28*10)/AB28 -> 5.8595041
A29: 罗源 | B29: 71 | C29: 3 | D29: 3 | F29: 11 | G29: 2 | H29: 2 | I29: 4 | J29: 4 | K29: 12 | L29: 112 | M29: =(B29*1+C29*2+D29*3+E29*4+F29*5+G29*6+H29*7+I29*8+J29*9+K29*10)/L29 -> 3.1696429 | Q29: 罗源 | R29: 73 | S29: 3 | T29: 2 | V29: 5 | W29: 1 | X29: 9 | Y29: 4 | Z29: 1 | AA29: 14 | AB29: 112 | AC29: =(R29*1+S29*2+T29*3+U29*4+V29*5+W29*6+X29*7+Y29*8+Z29*9+AA29*10)/AB29 -> 3.2142857
A30: 闽江 | B30: 4 | D30: 1 | F30: 3 | G30: 2 | H30: 1 | I30: 6 | J30: 1 | K30: 16 | L30: 34 | M30: =(B30*1+C30*2+D30*3+E30*4+F30*5+G30*6+H30*7+I30*8+J30*9+K30*10)/L30 -> 7.5882353 | Q30: 闽江 | R30: 9 | V30: 2 | W30: 1 | X30: 1 | Y30: 3 | Z30: 2 | AA30: 6 | AB30: 24 | AC30: =(R30*1+S30*2+T30*3+U30*4+V30*5+W30*6+X30*7+Y30*8+Z30*9+AA30*10)/AB30 -> 5.5833333
A31: 宁波 | B31: 41 | C31: 2 | D31: 4 | F31: 24 | G31: 7 | H31: 9 | I31: 12 | J31: 6 | K31: 39 | L31: 144 | M31: =(B31*1+C31*2+D31*3+E31*4+F31*5+G31*6+H31*7+I31*8+J31*9+K31*10)/L31 -> 5.7083333 | Q31: 宁波 | R31: 75 | T31: 5 | U31: 2 | V31: 13 | W31: 4 | X31: 10 | Y31: 20 | Z31: 7 | AA31: 60 | AB31: 196 | AC31: =(R31*1+S31*2+T31*3+U31*4+V31*5+W31*6+X31*7+Y31*8+Z31*9+AA31*10)/AB31 -> 5.5102041
A32: 腾冲 | B32: 3 | G32: 1 | H32: 1 | I32: 1 | K32: 2 | L32: 8 | M32: =(B32*1+C32*2+D32*3+E32*4+F32*5+G32*6+H32*7+I32*8+J32*9+K32*10)/L32 -> 5.5 | Q32: 腾冲 | R32: 54 | V32: 4 | Y32: 3 | Z32: 1 | AA32: 4 | AB32: 66 | AC32: =(R32*1+S32*2+T32*3+U32*4+V32*5+W32*6+X32*7+Y32*8+Z32*9+AA32*10)/AB32 -> 2.2272727
A33: 长沙 | B33: 21 | F33: 4 | G33: 4 | H33: 5 | I33: 6 | J33: 5 | K33: 20 | L33: 65 | M33: =(B33*1+C33*2+D33*3+E33*4+F33*5+G33*6+H33*7+I33*8+J33*9+K33*10)/L33 -> 6.0461538 | Q33: 长沙 | R33: 38 | T33: 5 | U33: 2 | V33: 5 | W33: 3 | X33: 3 | Y33: 7 | Z33: 7 | AA33: 21 | AB33: 91 | AC33: =(R33*1+S33*2+T33*3+U33*4+V33*5+W33*6+X33*7+Y33*8+Z33*9+AA33*10)/AB33 -> 4.989011
A34: 总计 | B34: =SUM(B21:B33) -> 353 | C34: =SUM(C21:C33) -> 10 | D34: =SUM(D21:D33) -> 22 | E34: =SUM(E21:E33) -> 5 | F34: =SUM(F21:F33) -> 88 | G34: =SUM(G21:G33) -> 46 | H34: =SUM(H21:H33) -> 34 | I34: =SUM(I21:I33) -> 91 | ... L34: =SUM(L21:L33) -> 1004 | M34: =(B34*1+C34*2+D34*3+E34*4+F34*5+G34*6+H34*7+I34*8+J34*9+K34*10)/L34 -> 5.6085657 | Q34: 总计 | R34: =SUM(R21:R33) -> 464 | S34: =SUM(S21:S33) -> 13 | T34: =SUM(T21:T33) -> 36 | U34: =SUM(U21:U33) -> 5 | V34: =SUM(V21:V33) -> 58 | W34: =SUM(W21:W33) -> 35 | X34: =SUM(X21:X33) -> 41 | Y34: =SUM(Y21:Y33) -> 112 | ... AB34: =SUM(AB21:AB33) -> 1158 | AC34: =(R34*1+S34*2+T34*3+U34*4+V34*5+W34*6+X34*7+Y34*8+Z34*9+AA34*10)/AB34 -> 5.3333333
A37: 5月 | Q37: 6月
A38: 公司 | B38: 1分 | C38: 2分 | D38: 3分 | E38: 4分 | F38: 5分 | G38: 6分 | H38: 7分 | I38: 8分 | J38: 9分 | K38: 10分 | L38: 合计 | M38: 满意度 | Q38: 公司 | R38: 1分 | S38: 2分 | T38: 3分 | U38: 4分 | V38: 5分 | W38: 6分 | X38: 7分 | Y38: 8分 | Z38: 9分 | AA38: 10分 | AB38: 合计 | AC38: 满意度
A39: 版纳 | B39: 11 | F39: 11 | G39: 2 | H39: 2 | I39: 4 | J39: 2 | K39: 32 | L39: 64 | M39: =(B39*1+C39*2+D39*3+E39*4+F39*5+G39*6+H39*7+I39*8+J39*9+K39*10)/L39 -> 7.21875 | Q39: 版纳 | AC39: =(R39*1+S39*2+T39*3+U39*4+V39*5+W39*6+X39*7+Y39*8+Z39*9+AA39*10)/AB39 -> #DIV/0!
A40: 北城 | B40: 49 | E40: 1 | F40: 4 | G40: 4 | H40: 12 | I40: 12 | J40: 4 | K40: 32 | L40: 118 | M40: =(B40*1+C40*2+D40*3+E40*4+F40*5+G40*6+H40*7+I40*8+J40*9+K40*10)/L40 -> 5.3644068 | Q40: 北城 | AC40: =(R40*1+S40*2+T40*3+U40*4+V40*5+W40*6+X40*7+Y40*8+Z40*9+AA40*10)/AB40 -> #DIV/0!
A41: 北京 | B41: 20 | E41: 1 | F41: 4 | G41: 1 | H41: 3 | I41: 3 | J41: 2 | K41: 21 | L41: 55 | M41: =(B41*1+C41*2+D41*3+E41*4+F41*5+G41*6+H41*7+I41*8+J41*9+K41*10)/L41 -> 5.8727273 | Q41: 北京 | AC41: =(R41*1+S41*2+T41*3+U41*4+V41*5+W41*6+X41*7+Y41*8+Z41*9+AA41*10)/AB41 -> #DIV/0!
A42: 滨湖 | B42: 39 | C42: 2 | D42: 2 | E42: 2 | F42: 7 | G42: 1 | H42: 1 | I42: 16 | J42: 6 | K42: 38 | L42: 114 | M42: =(B42*1+C42*2+D42*3+E42*4+F42*5+G42*6+H42*7+I42*8+J42*9+K42*10)/L42 -> 5.8508772 | Q42: 滨湖 | AC42: =(R42*1+S42*2+T42*3+U42*4+V42*5+W42*6+X42*7+Y42*8+Z42*9+AA42*10)/AB42 -> #DIV/0!
A43: 阜阳 | B43: 5 | F43: 1 | G43: 1 | I43: 2 | J43: 1 | K43: 9 | L43: 19 | M43: =(B43*1+C43*2+D43*3+E43*4+F43*5+G43*6+H43*7+I43*8+J43*9+K43*10)/L43 -> 6.8947368 | Q43: 阜阳 | AC43: =(R43*1+S43*2+T43*3+U43*4+V43*5+W43*6+X43*7+Y43*8+Z43*9+AA43*10)/AB43 -> #DIV/0!
A44: 贵阳 | B44: 22 | F44: 3 | G44: 5 | H44: 3 | I44: 20 | J44: 9 | K44: 48 | L44: 110 | M44: =(B44*1+C44*2+D44*3+E44*4+F44*5+G44*6+H44*7+I44*8+J44*9+K44*10)/L44 -> 7.3545455 | Q44: 贵阳 | AC44: =(R44*1+S44*2+T44*3+U44*4+V44*5+W44*6+X44*7+Y44*8+Z44*9+AA44*10)/AB44 -> #DIV/0!
A45: 昆明 | B45: 19 | C45: 1 | D45: 3 | F45: 9 | G45: 4 | H45: 3 | I45: 15 | J45: 9 | K45: 39 | L45: 102 | M45: =(B45*1+C45*2+D45*3+E45*4+F45*5+G45*6+H45*7+I45*8+J45*9+K45*10)/L45 -> 6.9705882 | Q45: 昆明 | AC45: =(R45*1+S45*2+T45*3+U45*4+V45*5+W45*6+X45*7+Y45*8+Z45*9+AA45*10)/AB45 -> #DIV/0!
A46: 连江 | B46: 55 | C46: 1 | D46: 5 | E46: 3 | F46: 5 | G46: 4 | H46: 4 | I46: 4 | J46: 10 | K46: 43 | L46: 134 | M46: =(B46*1+C46*2+D46*3+E46*4+F46*5+G46*6+H46*7+I46*8+J46*9+K46*10)/L46 -> 5.3208955 | Q46: 连江 | AC46: =(R46*1+S46*2+T46*3+U46*4+V46*5+W46*6+X46*7+Y46*8+Z46*9+AA46*10)/AB46 -> #DIV/0!
A47: 罗源 | B47: 49 | C47: 1 | D47: 2 | F47: 8 | H47: 1 | I47: 6 | J47: 5 | K47: 15 | L47: 87 | M47: =(B47*1+C47*2+D47*3+E47*4+F47*5+G47*6+H47*7+I47*8+J47*9+K47*10)/L47 -> 3.9885057 | Q47: 罗源 | AC47: =(R47*1+S47*2+T47*3+U47*4+V47*5+W47*6+X47*7+Y47*8+Z47*9+AA47*10)/AB47 -> #DIV/0!
A48: 闽江 | B48: 4 | D48: 1 | G48: 2 | J48: 2 | K48: 3 | L48: 12 | M48: =(B48*1+C48*2+D48*3+E48*4+F48*5+G48*6+H48*7+I48*8+J48*9+K48*10)/L48 -> 5.5833333 | Q48: 闽江 | AC48: =(R48*1+S48*2+T48*3+U48*4+V48*5+W48*6+X48*7+Y48*8+Z48*9+AA48*10)/AB48 -> #DIV/0!
A49: 宁波 | B49: 53 | C49: 1 | D49: 1 | F49: 18 | G49: 6 | H49: 9 | I49: 20 | J49: 5 | K49: 63 | L49: 176 | M49: =(B49*1+C49*2+D49*3+E49*4+F49*5+G49*6+H49*7+I49*8+J49*9+K49*10)/L49 -> 6.1477273 | Q49: 宁波 | AC49: =(R49*1+S49*2+T49*3+U49*4+V49*5+W49*6+X49*7+Y49*8+Z49*9+AA49*10)/AB49 -> #DIV/0!
A50: 腾冲 | B50: 11 | C50: 2 | F50: 2 | I50: 3 | J50: 2 | K50: 5 | L50: 25 | M50: =(B50*1+C50*2+D50*3+E50*4+F50*5+G50*6+H50*7+I50*8+J50*9+K50*10)/L50 -> 4.68 | Q50: 腾冲 | AC50: =(R50*1+S50*2+T50*3+U50*4+V50*5+W50*6+X50*7+Y50*8+Z50*9+AA50*10)/AB50 -> #DIV/0!
A51: 长沙 | B51: 35 | D51: 2 | F51: 12 | G51: 3 | I51: 14 | J51: 3 | K51: 26 | L51: 95 | M51: =(B51*1+C51*2+D51*3+E51*4+F51*5+G51*6+H51*7+I51*8+J51*9+K51*10)/L51 -> 5.4526316 | Q51: 长沙 | AC51: =(R51*1+S51*2+T51*3+U51*4+V51*5+W51*6+X51*7+Y51*8+Z51*9+AA51*10)/AB51 -> #DIV/0!
A52: 总计 | B52: =SUM(B39:B51) -> 372 | C52: =SUM(C39:C51) -> 8 | D52: =SUM(D39:D51) -> 16 | E52: =SUM(E39:E51) -> 7 | F52: =SUM(F39:F51) -> 84 | G52: =SUM(G39:G51) -> 33 | H52: =SUM(H39:H51) -> 38 | I52: =SUM(I39:I51) -> 119 | ... L52: =SUM(L39:L51) -> 1111 | M52: =(B52*1+C52*2+D52*3+E52*4+F52*5+G52*6+H52*7+I52*8+J52*9+K52*10)/L52 -> 5.9225923 | Q52: 总计 | R52: =SUM(R39:R51) -> 0 | S52: =SUM(S39:S51) -> 0 | T52: =SUM(T39:T51) -> 0 | U52: =SUM(U39:U51) -> 0 | V52: =SUM(V39:V51) -> 0 | W52: =SUM(W39:W51) -> 0 | X52: =SUM(X39:X51) -> 0 | Y52: =SUM(Y39:Y51) -> 0 | ... AB52: =SUM(AB39:AB51) -> 0 | AC52: =(R52*1+S52*2+T52*3+U52*4+V52*5+W52*6+X52*7+Y52*8+Z52*9+AA52*10)/AB52 -> #DIV/0!
A55: 7月 | Q55: 8月
A56: 公司 | B56: 1分 | C56: 2分 | D56: 3分 | E56: 4分 | F56: 5分 | G56: 6分 | H56: 7分 | I56: 8分 | J56: 9分 | K56: 10分 | L56: 合计 | M56: 满意度 | Q56: 公司 | R56: 1分 | S56: 2分 | T56: 3分 | U56: 4分 | V56: 5分 | W56: 6分 | X56: 7分 | Y56: 8分 | Z56: 9分 | AA56: 10分 | AB56: 合计 | AC56: 满意度
A57: 版纳 | M57: =(B57*1+C57*2+D57*3+E57*4+F57*5+G57*6+H57*7+I57*8+J57*9+K57*10)/L57 -> #DIV/0! | Q57: 版纳 | AC57: =(R57*1+S57*2+T57*3+U57*4+V57*5+W57*6+X57*7+Y57*8+Z57*9+AA57*10)/AB57 -> #DIV/0!
A58: 北城 | M58: =(B58*1+C58*2+D58*3+E58*4+F58*5+G58*6+H58*7+I58*8+J58*9+K58*10)/L58 -> #DIV/0! | Q58: 北城 | AC58: =(R58*1+S58*2+T58*3+U58*4+V58*5+W58*6+X58*7+Y58*8+Z58*9+AA58*10)/AB58 -> #DIV/0!
A59: 北京 | M59: =(B59*1+C59*2+D59*3+E59*4+F59*5+G59*6+H59*7+I59*8+J59*9+K59*10)/L59 -> #DIV/0! | Q59: 北京 | AC59: =(R59*1+S59*2+T59*3+U59*4+V59*5+W59*6+X59*7+Y59*8+Z59*9+AA59*10)/AB59 -> #DIV/0!
A60: 滨湖 | M60: =(B60*1+C60*2+D60*3+E60*4+F60*5+G60*6+H60*7+I60*8+J60*9+K60*10)/L60 -> #DIV/0! | Q60: 滨湖 | AC60: =(R60*1+S60*2+T60*3+U60*4+V60*5+W60*6+X60*7+Y60*8+Z60*9+AA60*10)/AB60 -> #DIV/0!
A61: 阜阳 | M61: =(B61*1+C61*2+D61*3+E61*4+F61*5+G61*6+H61*7+I61*8+J61*9+K61*10)/L61 -> #DIV/0! | Q61: 阜阳 | AC61: =(R61*1+S61*2+T61*3+U61*4+V61*5+W61*6+X61*7+Y61*8+Z61*9+AA61*10)/AB61 -> #DIV/0!
A62: 贵阳 | M62: =(B62*1+C62*2+D62*3+E62*4+F62*5+G62*6+H62*7+I62*8+J62*9+K62*10)/L62 -> #DIV/0! | Q62: 贵阳 | AC62: =(R62*1+S62*2+T62*3+U62*4+V62*5+W62*6+X62*7+Y62*8+Z62*9+AA62*10)/AB62 -> #DIV/0!
A63: 昆明 | M63: =(B63*1+C63*2+D63*3+E63*4+F63*5+G63*6+H63*7+I63*8+J63*9+K63*10)/L63 -> #DIV/0! | Q63: 昆明 | AC63: =(R63*1+S63*2+T63*3+U63*4+V63*5+W63*6+X63*7+Y63*8+Z63*9+AA63*10)/AB63 -> #DIV/0!
A64: 连江 | M64: =(B64*1+C64*2+D64*3+E64*4+F64*5+G64*6+H64*7+I64*8+J64*9+K64*10)/L64 -> #DIV/0! | Q64: 连江 | AC64: =(R64*1+S64*2+T64*3+U64*4+V64*5+W64*6+X64*7+Y64*8+Z64*9+AA64*10)/AB64 -> #DIV/0!
A65: 罗源 | M65: =(B65*1+C65*2+D65*3+E65*4+F65*5+G65*6+H65*7+I65*8+J65*9+K65*10)/L65 -> #DIV/0! | Q65: 罗源 | AC65: =(R65*1+S65*2+T65*3+U65*4+V65*5+W65*6+X65*7+Y65*8+Z65*9+AA65*10)/AB65 -> #DIV/0!
A66: 闽江 | M66: =(B66*1+C66*2+D66*3+E66*4+F66*5+G66*6+H66*7+I66*8+J66*9+K66*10)/L66 -> #DIV/0! | Q66: 闽江 | AC66: =(R66*1+S66*2+T66*3+U66*4+V66*5+W66*6+X66*7+Y66*8+Z66*9+AA66*10)/AB66 -> #DIV/0!
A67: 宁波 | M67: =(B67*1+C67*2+D67*3+E67*4+F67*5+G67*6+H67*7+I67*8+J67*9+K67*10)/L67 -> #DIV/0! | Q67: 宁波 | AC67: =(R67*1+S67*2+T67*3+U67*4+V67*5+W67*6+X67*7+Y67*8+Z67*9+AA67*10)/AB67 -> #DIV/0!
A68: 腾冲 | M68: =(B68*1+C68*2+D68*3+E68*4+F68*5+G68*6+H68*7+I68*8+J68*9+K68*10)/L68 -> #DIV/0! | Q68: 腾冲 | AC68: =(R68*1+S68*2+T68*3+U68*4+V68*5+W68*6+X68*7+Y68*8+Z68*9+AA68*10)/AB68 -> #DIV/0!
... A70: 总计 | M70: =(B70*1+C70*2+D70*3+E70*4+F70*5+G70*6+H70*7+I70*8+J70*9+K70*10)/L70 -> #DIV/0! | Q70: 总计 | AC70: =(R70*1+S70*2+T70*3+U70*4+V70*5+W70*6+X70*7+Y70*8+Z70*9+AA70*10)/AB70 -> #DIV/0!
A73: 9月 | Q73: 10月
A74: 公司 | B74: 1分 | C74: 2分 | D74: 3分 | E74: 4分 | F74: 5分 | G74: 6分 | H74: 7分 | I74: 8分 | J74: 9分 | K74: 10分 | L74: 合计 | M74: 满意度 | Q74: 公司 | R74: 1分 | S74: 2分 | T74: 3分 | U74: 4分 | V74: 5分 | W74: 6分 | X74: 7分 | Y74: 8分 | Z74: 9分 | AA74: 10分 | AB74: 合计 | AC74: 满意度
A75: 版纳 | M75: =(B75*1+C75*2+D75*3+E75*4+F75*5+G75*6+H75*7+I75*8+J75*9+K75*10)/L75 -> #DIV/0! | Q75: 版纳 | AC75: =(R75*1+S75*2+T75*3+U75*4+V75*5+W75*6+X75*7+Y75*8+Z75*9+AA75*10)/AB75 -> #DIV/0!
A76: 北城 | M76: =(B76*1+C76*2+D76*3+E76*4+F76*5+G76*6+H76*7+I76*8+J76*9+K76*10)/L76 -> #DIV/0! | Q76: 北城 | AC76: =(R76*1+S76*2+T76*3+U76*4+V76*5+W76*6+X76*7+Y76*8+Z76*9+AA76*10)/AB76 -> #DIV/0!
A77: 北京 | M77: =(B77*1+C77*2+D77*3+E77*4+F77*5+G77*6+H77*7+I77*8+J77*9+K77*10)/L77 -> #DIV/0! | Q77: 北京 | AC77: =(R77*1+S77*2+T77*3+U77*4+V77*5+W77*6+X77*7+Y77*8+Z77*9+AA77*10)/AB77 -> #DIV/0!
A78: 滨湖 | M78: =(B78*1+C78*2+D78*3+E78*4+F78*5+G78*6+H78*7+I78*8+J78*9+K78*10)/L78 -> #DIV/0! | Q78: 滨湖 | AC78: =(R78*1+S78*2+T78*3+U78*4+V78*5+W78*6+X78*7+Y78*8+Z78*9+AA78*10)/AB78 -> #DIV/0!
A79: 阜阳 | M79: =(B79*1+C79*2+D79*3+E79*4+F79*5+G79*6+H79*7+I79*8+J79*9+K79*10)/L79 -> #DIV/0! | Q79: 阜阳 | AC79: =(R79*1+S79*2+T79*3+U79*4+V79*5+W79*6+X79*7+Y79*8+Z79*9+AA79*10)/AB79 -> #DIV/0!
A80: 贵阳 | M80: =(B80*1+C80*2+D80*3+E80*4+F80*5+G80*6+H80*7+I80*8+J80*9+K80*10)/L80 -> #DIV/0! | Q80: 贵阳 | AC80: =(R80*1+S80*2+T80*3+U80*4+V80*5+W80*6+X80*7+Y80*8+Z80*9+AA80*10)/AB80 -> #DIV/0!
A81: 昆明 | M81: =(B81*1+C81*2+D81*3+E81*4+F81*5+G81*6+H81*7+I81*8+J81*9+K81*10)/L81 -> #DIV/0! | Q81: 昆明 | AC81: =(R81*1+S81*2+T81*3+U81*4+V81*5+W81*6+X81*7+Y81*8+Z81*9+AA81*10)/AB81 -> #DIV/0!
A82: 连江 | M82: =(B82*1+C82*2+D82*3+E82*4+F82*5+G82*6+H82*7+I82*8+J82*9+K82*10)/L82 -> #DIV/0! | Q82: 连江 | AC82: =(R82*1+S82*2+T82*3+U82*4+V82*5+W82*6+X82*7+Y82*8+Z82*9+AA82*10)/AB82 -> #DIV/0!
A83: 罗源 | M83: =(B83*1+C83*2+D83*3+E83*4+F83*5+G83*6+H83*7+I83*8+J83*9+K83*10)/L83 -> #DIV/0! | Q83: 罗源 | AC83: =(R83*1+S83*2+T83*3+U83*4+V83*5+W83*6+X83*7+Y83*8+Z83*9+AA83*10)/AB83 -> #DIV/0!
A84: 闽江 | M84: =(B84*1+C84*2+D84*3+E84*4+F84*5+G84*6+H84*7+I84*8+J84*9+K84*10)/L84 -> #DIV/0! | Q84: 闽江 | AC84: =(R84*1+S84*2+T84*3+U84*4+V84*5+W84*6+X84*7+Y84*8+Z84*9+AA84*10)/AB84 -> #DIV/0!
A85: 宁波 | M85: =(B85*1+C85*2+D85*3+E85*4+F85*5+G85*6+H85*7+I85*8+J85*9+K85*10)/L85 -> #DIV/0! | Q85: 宁波 | AC85: =(R85*1+S85*2+T85*3+U85*4+V85*5+W85*6+X85*7+Y85*8+Z85*9+AA85*10)/AB85 -> #DIV/0!
A86: 腾冲 | M86: =(B86*1+C86*2+D86*3+E86*4+F86*5+G86*6+H86*7+I86*8+J86*9+K86*10)/L86 -> #DIV/0! | Q86: 腾冲 | AC86: =(R86*1+S86*2+T86*3+U86*4+V86*5+W86*6+X86*7+Y86*8+Z86*9+AA86*10)/AB86 -> #DIV/0!
... A88: 总计 | M88: =(B88*1+C88*2+D88*3+E88*4+F88*5+G88*6+H88*7+I88*8+J88*9+K88*10)/L88 -> #DIV/0! | Q88: 总计 | AC88: =(R88*1+S88*2+T88*3+U88*4+V88*5+W88*6+X88*7+Y88*8+Z88*9+AA88*10)/AB88 -> #DIV/0!
A91: 11月 | Q91: 12月
A92: 公司 | B92: 1分 | C92: 2分 | D92: 3分 | E92: 4分 | F92: 5分 | G92: 6分 | H92: 7分 | I92: 8分 | J92: 9分 | K92: 10分 | L92: 合计 | M92: 满意度 | Q92: 公司 | R92: 1分 | S92: 2分 | T92: 3分 | U92: 4分 | V92: 5分 | W92: 6分 | X92: 7分 | Y92: 8分 | Z92: 9分 | AA92: 10分 | AB92: 合计 | AC92: 满意度
A93: 版纳 | M93: =(B93*1+C93*2+D93*3+E93*4+F93*5+G93*6+H93*7+I93*8+J93*9+K93*10)/L93 -> #DIV/0! | Q93: 版纳 | AC93: =(R93*1+S93*2+T93*3+U93*4+V93*5+W93*6+X93*7+Y93*8+Z93*9+AA93*10)/AB93 -> #DIV/0!
A94: 北城 | M94: =(B94*1+C94*2+D94*3+E94*4+F94*5+G94*6+H94*7+I94*8+J94*9+K94*10)/L94 -> #DIV/0! | Q94: 北城 | AC94: =(R94*1+S94*2+T94*3+U94*4+V94*5+W94*6+X94*7+Y94*8+Z94*9+AA94*10)/AB94 -> #DIV/0!
A95: 北京 | M95: =(B95*1+C95*2+D95*3+E95*4+F95*5+G95*6+H95*7+I95*8+J95*9+K95*10)/L95 -> #DIV/0! | Q95: 北京 | AC95: =(R95*1+S95*2+T95*3+U95*4+V95*5+W95*6+X95*7+Y95*8+Z95*9+AA95*10)/AB95 -> #DIV/0!
A96: 滨湖 | M96: =(B96*1+C96*2+D96*3+E96*4+F96*5+G96*6+H96*7+I96*8+J96*9+K96*10)/L96 -> #DIV/0! | Q96: 滨湖 | AC96: =(R96*1+S96*2+T96*3+U96*4+V96*5+W96*6+X96*7+Y96*8+Z96*9+AA96*10)/AB96 -> #DIV/0!
A97: 阜阳 | M97: =(B97*1+C97*2+D97*3+E97*4+F97*5+G97*6+H97*7+I97*8+J97*9+K97*10)/L97 -> #DIV/0! | Q97: 阜阳 | AC97: =(R97*1+S97*2+T97*3+U97*4+V97*5+W97*6+X97*7+Y97*8+Z97*9+AA97*10)/AB97 -> #DIV/0!
A98: 贵阳 | M98: =(B98*1+C98*2+D98*3+E98*4+F98*5+G98*6+H98*7+I98*8+J98*9+K98*10)/L98 -> #DIV/0! | Q98: 贵阳 | AC98: =(R98*1+S98*2+T98*3+U98*4+V98*5+W98*6+X98*7+Y98*8+Z98*9+AA98*10)/AB98 -> #DIV/0!
A99: 昆明 | M99: =(B99*1+C99*2+D99*3+E99*4+F99*5+G99*6+H99*7+I99*8+J99*9+K99*10)/L99 -> #DIV/0! | Q99: 昆明 | AC99: =(R99*1+S99*2+T99*3+U99*4+V99*5+W99*6+X99*7+Y99*8+Z99*9+AA99*10)/AB99 -> #DIV/0!
A100: 连江 | M100: =(B100*1+C100*2+D100*3+E100*4+F100*5+G100*6+H100*7+I100*8+J100*9+K100*10)/L100 -> #DIV/0! | Q100: 连江 | AC100: =(R100*1+S100*2+T100*3+U100*4+V100*5+W100*6+X100*7+Y100*8+Z100*9+AA100*10)/AB100 -> #DIV/0!
A101: 罗源 | M101: =(B101*1+C101*2+D101*3+E101*4+F101*5+G101*6+H101*7+I101*8+J101*9+K101*10)/L101 -> #DIV/0! | Q101: 罗源 | AC101: =(R101*1+S101*2+T101*3+U101*4+V101*5+W101*6+X101*7+Y101*8+Z101*9+AA101*10)/AB101 -> #DIV/0!
A102: 闽江 | M102: =(B102*1+C102*2+D102*3+E102*4+F102*5+G102*6+H102*7+I102*8+J102*9+K102*10)/L102 -> #DIV/0! | Q102: 闽江 | AC102: =(R102*1+S102*2+T102*3+U102*4+V102*5+W102*6+X102*7+Y102*8+Z102*9+AA102*10)/AB102 -> #DIV/0!
A103: 宁波 | M103: =(B103*1+C103*2+D103*3+E103*4+F103*5+G103*6+H103*7+I103*8+J103*9+K103*10)/L103 -> #DIV/0! | Q103: 宁波 | AC103: =(R103*1+S103*2+T103*3+U103*4+V103*5+W103*6+X103*7+Y103*8+Z103*9+AA103*10)/AB103 -> #DIV/0!
A104: 腾冲 | M104: =(B104*1+C104*2+D104*3+E104*4+F104*5+G104*6+H104*7+I104*8+J104*9+K104*10)/L104 -> #DIV/0! | Q104: 腾冲 | AC104: =(R104*1+S104*2+T104*3+U104*4+V104*5+W104*6+X104*7+Y104*8+Z104*9+AA104*10)/AB104 -> #DIV/0!
... A106: 总计 | M106: =(B106*1+C106*2+D106*3+E106*4+F106*5+G106*6+H106*7+I106*8+J106*9+K106*10)/L106 -> #DIV/0! | Q106: 总计 | AC106: =(R106*1+S106*2+T106*3+U106*4+V106*5+W106*6+X106*7+Y106*8+Z106*9+AA106*10)/AB106 -> #DIV/0!
A109: 总计
A110: 公司 | B110: 1分 | C110: 2分 | D110: 3分 | E110: 4分 | F110: 5分 | G110: 6分 | H110: 7分 | I110: 8分 | J110: 9分 | K110: 10分 | L110: 合计 | M110: 满意度
A111: 版纳 | B111: =B3+R3+B21+R21+B39+R39+B57+R57+B75+R75+B93+R93 -> 82 | C111: =C3+S3+C21+S21+C39+S39+C57+S57+C75+S75+C93+S93 -> 8 | D111: =D3+T3+D21+T21+D39+T39+D57+T57+D75+T75+D93+T93 -> 3 | E111: =E3+U3+E21+U21+E39+U39+E57+U57+E75+U75+E93+U93 -> 2 | F111: =F3+V3+F21+V21+F39+V39+F57+V57+F75+V75+F93+V93 -> 31 | G111: =G3+W3+G21+W21+G39+W39+G57+W57+G75+W75+G93+W93 -> 7 | H111: =H3+X3+H21+X21+H39+X39+H57+X57+H75+X75+H93+X93 -> 7 | I111: =I3+Y3+I21+Y21+I39+Y39+I57+Y57+I75+Y75+I93+Y93 -> 20 | ... K111: =K3+AA3+K21+AA21+K39+AA39+K57+AA57+K75+AA75+K93+AA93 -> 75 | L111: =SUM(B111:K111) -> 249 | M111: =(B111*1+C111*2+D111*3+E111*4+F111*5+G111*6+H111*7+I111*8+J111*9+K111*10)/L111 -> 5.6104418
A112: 北城 | B112: =B4+R4+B22+R22+B40+R40+B58+R58+B76+R76+B94+R94 -> 168 | C112: =C4+S4+C22+S22+C40+S40+C58+S58+C76+S76+C94+S94 -> 3 | D112: =D4+T4+D22+T22+D40+T40+D58+T58+D76+T76+D94+T94 -> 7 | E112: =E4+U4+E22+U22+E40+U40+E58+U58+E76+U76+E94+U94 -> 1 | F112: =F4+V4+F22+V22+F40+V40+F58+V58+F76+V76+F94+V94 -> 32 | G112: =G4+W4+G22+W22+G40+W40+G58+W58+G76+W76+G94+W94 -> 20 | H112: =H4+X4+H22+X22+H40+X40+H58+X58+H76+X76+H94+X94 -> 16 | I112: =I4+Y4+I22+Y22+I40+Y40+I58+Y58+I76+Y76+I94+Y94 -> 35 | ... K112: =K4+AA4+K22+AA22+K40+AA40+K58+AA58+K76+AA76+K94+AA94 -> 112 | L112: =SUM(B112:K112) -> 405 | M112: =(B112*1+C112*2+D112*3+E112*4+F112*5+G112*6+H112*7+I112*8+J112*9+K112*10)/L112 -> 5.1604938
A113: 北京 | B113: =B5+R5+B23+R23+B41+R41+B59+R59+B77+R77+B95+R95 -> 83 | C113: =C5+S5+C23+S23+C41+S41+C59+S59+C77+S77+C95+S95 -> 1 | D113: =D5+T5+D23+T23+D41+T41+D59+T59+D77+T77+D95+T95 -> 19 | E113: =E5+U5+E23+U23+E41+U41+E59+U59+E77+U77+E95+U95 -> 1 | F113: =F5+V5+F23+V23+F41+V41+F59+V59+F77+V77+F95+V95 -> 14 | G113: =G5+W5+G23+W23+G41+W41+G59+W59+G77+W77+G95+W95 -> 8 | H113: =H5+X5+H23+X23+H41+X41+H59+X59+H77+X77+H95+X95 -> 11 | I113: =I5+Y5+I23+Y23+I41+Y41+I59+Y59+I77+Y77+I95+Y95 -> 29 | ... K113: =K5+AA5+K23+AA23+K41+AA41+K59+AA59+K77+AA77+K95+AA95 -> 96 | L113: =SUM(B113:K113) -> 281 | M113: =(B113*1+C113*2+D113*3+E113*4+F113*5+G113*6+H113*7+I113*8+J113*9+K113*10)/L113 -> 6.0640569
A114: 滨湖 | B114: =B6+R6+B24+R24+B42+R42+B60+R60+B78+R78+B96+R96 -> 198 | C114: =C6+S6+C24+S24+C42+S42+C60+S60+C78+S78+C96+S96 -> 5 | D114: =D6+T6+D24+T24+D42+T42+D60+T60+D78+T78+D96+T96 -> 7 | E114: =E6+U6+E24+U24+E42+U42+E60+U60+E78+U78+E96+U96 -> 4 | F114: =F6+V6+F24+V24+F42+V42+F60+V60+F78+V78+F96+V96 -> 29 | G114: =G6+W6+G24+W24+G42+W42+G60+W60+G78+W78+G96+W96 -> 20 | H114: =H6+X6+H24+X24+H42+X42+H60+X60+H78+X78+H96+X96 -> 17 | I114: =I6+Y6+I24+Y24+I42+Y42+I60+Y60+I78+Y78+I96+Y96 -> 45 | ... K114: =K6+AA6+K24+AA24+K42+AA42+K60+AA60+K78+AA78+K96+AA96 -> 120 | L114: =SUM(B114:K114) -> 469 | M114: =(B114*1+C114*2+D114*3+E114*4+F114*5+G114*6+H114*7+I114*8+J114*9+K114*10)/L114 -> 5.1279318
A115: 阜阳 | B115: =B7+R7+B25+R25+B43+R43+B61+R61+B79+R79+B97+R97 -> 47 | C115: =C7+S7+C25+S25+C43+S43+C61+S61+C79+S79+C97+S97 -> 0 | D115: =D7+T7+D25+T25+D43+T43+D61+T61+D79+T79+D97+T97 -> 0 | E115: =E7+U7+E25+U25+E43+U43+E61+U61+E79+U79+E97+U97 -> 0 | F115: =F7+V7+F25+V25+F43+V43+F61+V61+F79+V79+F97+V97 -> 11 | G115: =G7+W7+G25+W25+G43+W43+G61+W61+G79+W79+G97+W97 -> 1 | H115: =H7+X7+H25+X25+H43+X43+H61+X61+H79+X79+H97+X97 -> 1 | I115: =I7+Y7+I25+Y25+I43+Y43+I61+Y61+I79+Y79+I97+Y97 -> 4 | ... K115: =K7+AA7+K25+AA25+K43+AA43+K61+AA61+K79+AA79+K97+AA97 -> 25 | L115: =SUM(B115:K115) -> 93 | M115: =(B115*1+C115*2+D115*3+E115*4+F115*5+G115*6+H115*7+I115*8+J115*9+K115*10)/L115 -> 4.655914
...

Sheet 入户维修
A3: 2026报修总单量
A4: 公司 | B4: 1月 | C4: 2月 | D4: 3月 | E4: 4月 | F4: 5月 | G4: 6月 | H4: 7月 | I4: 8月 | J4: 9月 | K4: 10月 | L4: 11月 | M4: 12月 | N4: 总计
A5: 版纳
A6: 北城
A7: 北京
A8: 滨湖
A9: 阜阳
A10: 贵阳
A11: 昆明
A12: 连江
A13: 罗源
A14: 闽江
A15: 宁波
A16: 腾冲
A17: 长沙
A18: 总计 | B18: =SUM(B5:B17) -> 0 | C18: =SUM(C5:C17) -> 0 | D18: =SUM(D5:D17) -> 0 | E18: =SUM(E5:E17) -> 0 | F18: =SUM(F5:F17) -> 0 | G18: =SUM(G5:G17) -> 0 | H18: =SUM(H5:H17) -> 0 | I18: =SUM(I5:I17) -> 0 | ... N18: =SUM(N5:N17) -> 0
